<?xml version="1.0"?>
<?xml-stylesheet type="text/xsl" href="style.xsl"?>
<STAT>
<TAG>ALL</TAG>
<VAR>Q2m</VAR>
<UNIT>g/Kg</UNIT>
<PERIOD>20211110-20211201</PERIOD>
 <STATION>
 <MEAN_OBS>  0.979578435     </MEAN_OBS>
 <STDV_OBS>  0.372120261     </STDV_OBS>
 <EXP>
 <ID>        1024 </ID>
 <NAME>REF</NAME>
 <NUM>        3000 </NUM>
 <MEAN>  0.821838796     </MEAN>
 <STDV> -0.317637920     </STDV>
 <BIAS>  0.183304861     </BIAS>
 <RMSE>  0.876668394     </RMSE>
 <CORR>  -6.42552866E-20 </CORR>
 </EXP>
 <EXP>
 <ID>        1024 </ID>
 <NAME>SCATT</NAME>
 <NUM>        3000 </NUM>
 <MEAN>   1.40129846E-45 </MEAN>
 <STDV>   1.40129846E-45 </STDV>
 <BIAS>  0.180304438     </BIAS>
 <RMSE>  0.880798817     </RMSE>
 <CORR>   0.00000000     </CORR>
 </EXP>
 </STATION>
 <STATION>
 <MEAN_OBS>   3.87802696     </MEAN_OBS>
 <STDV_OBS>   1.21045744     </STDV_OBS>
 <EXP>
 <ID>        1115 </ID>
 <NAME>REF</NAME>
 <NUM>        3194 </NUM>
 <MEAN>   3.73195624     </MEAN>
 <STDV>   5.66106606E-11 </STDV>
 <BIAS>  0.388563931     </BIAS>
 <RMSE>  0.947811425     </RMSE>
 <CORR>   5.65693603E-11 </CORR>
 </EXP>
 <EXP>
 <ID>        1115 </ID>
 <NAME>SCATT</NAME>
 <NUM>        3194 </NUM>
 <MEAN>   1.40129846E-45 </MEAN>
 <STDV>   1.40129846E-45 </STDV>
 <BIAS>  0.382476568     </BIAS>
 <RMSE>  0.949921668     </RMSE>
 <CORR>   1.40129846E-45 </CORR>
 </EXP>
 </STATION>
 <STATION>
 <MEAN_OBS>  0.632983983     </MEAN_OBS>
 <STDV_OBS>  0.182887450     </STDV_OBS>
 <EXP>
 <ID>       20046 </ID>
 <NAME>REF</NAME>
 <NUM>        1172 </NUM>
 <MEAN>  0.627499998     </MEAN>
 <STDV>   5.65684721E-11 </STDV>
 <BIAS>  0.204756752     </BIAS>
 <RMSE>  0.527129769     </RMSE>
 <CORR>   5.65683611E-11 </CORR>
 </EXP>
 <EXP>
 <ID>       20046 </ID>
 <NAME>SCATT</NAME>
 <NUM>        1172 </NUM>
 <MEAN>   1.40129846E-45 </MEAN>
 <STDV>   1.40129846E-45 </STDV>
 <BIAS>  0.204198673     </BIAS>
 <RMSE>  0.527933657     </RMSE>
 <CORR>   1.40129846E-45 </CORR>
 </EXP>
 </STATION>
 <STATION>
 <MEAN_OBS>   2.41922545     </MEAN_OBS>
 <STDV_OBS>   1.08661532     </STDV_OBS>
 <EXP>
 <ID>        1046 </ID>
 <NAME>REF</NAME>
 <NUM>        3194 </NUM>
 <MEAN>   2.51172519     </MEAN>
 <STDV>   5.65694713E-11 </STDV>
 <BIAS>  0.425929457     </BIAS>
 <RMSE>  0.917711437     </RMSE>
 <CORR>   5.65693603E-11 </CORR>
 </EXP>
 <EXP>
 <ID>        1046 </ID>
 <NAME>SCATT</NAME>
 <NUM>        3194 </NUM>
 <MEAN>   1.40129846E-45 </MEAN>
 <STDV>   1.40129846E-45 </STDV>
 <BIAS>  0.422920376     </BIAS>
 <RMSE>  0.921406627     </RMSE>
 <CORR>   1.40129846E-45 </CORR>
 </EXP>
 </STATION>
 <STATION>
 <MEAN_OBS>   1.42374635     </MEAN_OBS>
 <STDV_OBS>   1.14897144     </STDV_OBS>
 <EXP>
 <ID>        1065 </ID>
 <NAME>REF</NAME>
 <NUM>        3194 </NUM>
 <MEAN>   1.78865194     </MEAN>
 <STDV>   5.66107716E-11 </STDV>
 <BIAS>  0.541877151     </BIAS>
 <RMSE>  0.882158875     </RMSE>
 <CORR>   5.65683611E-11 </CORR>
 </EXP>
 <EXP>
 <ID>        1065 </ID>
 <NAME>SCATT</NAME>
 <NUM>        3194 </NUM>
 <MEAN>   1.40129846E-45 </MEAN>
 <STDV>   1.40129846E-45 </STDV>
 <BIAS>  0.533296764     </BIAS>
 <RMSE>  0.886066914     </RMSE>
 <CORR>   1.40129846E-45 </CORR>
 </EXP>
 </STATION>
 <STATION>
 <MEAN_OBS>   1.21420407     </MEAN_OBS>
 <STDV_OBS>  0.774865508     </STDV_OBS>
 <EXP>
 <ID>        1199 </ID>
 <NAME>REF</NAME>
 <NUM>        2252 </NUM>
 <MEAN>   1.22440922     </MEAN>
 <STDV> -0.317637920     </STDV>
 <BIAS>  0.452531755     </BIAS>
 <RMSE>  0.835881293     </RMSE>
 <CORR>   5.65693603E-11 </CORR>
 </EXP>
 <EXP>
 <ID>        1199 </ID>
 <NAME>SCATT</NAME>
 <NUM>        2252 </NUM>
 <MEAN>   1.40129846E-45 </MEAN>
 <STDV>   1.40129846E-45 </STDV>
 <BIAS>  0.440377533     </BIAS>
 <RMSE>  0.844861031     </RMSE>
 <CORR>   1.40129846E-45 </CORR>
 </EXP>
 </STATION>
 <STATION>
 <MEAN_OBS>   3.80812144     </MEAN_OBS>
 <STDV_OBS>   1.08500481     </STDV_OBS>
 <EXP>
 <ID>        1108 </ID>
 <NAME>REF</NAME>
 <NUM>        3194 </NUM>
 <MEAN>   3.69162679     </MEAN>
 <STDV>   5.66106606E-11 </STDV>
 <BIAS>  0.353880376     </BIAS>
 <RMSE>  0.947291911     </RMSE>
 <CORR>   5.65683611E-11 </CORR>
 </EXP>
 <EXP>
 <ID>        1108 </ID>
 <NAME>SCATT</NAME>
 <NUM>        3194 </NUM>
 <MEAN>   1.40129846E-45 </MEAN>
 <STDV>   1.40129846E-45 </STDV>
 <BIAS>  0.350635976     </BIAS>
 <RMSE>  0.947545767     </RMSE>
 <CORR>   1.40129846E-45 </CORR>
 </EXP>
 </STATION>
 <STATION>
 <MEAN_OBS>   3.73993182     </MEAN_OBS>
 <STDV_OBS>   1.12820065     </STDV_OBS>
 <EXP>
 <ID>        1112 </ID>
 <NAME>REF</NAME>
 <NUM>        3063 </NUM>
 <MEAN>   3.54333711     </MEAN>
 <STDV>   5.65694713E-11 </STDV>
 <BIAS>  0.351298660     </BIAS>
 <RMSE>  0.951068401     </RMSE>
 <CORR>   5.65683611E-11 </CORR>
 </EXP>
 <EXP>
 <ID>        1112 </ID>
 <NAME>SCATT</NAME>
 <NUM>        3063 </NUM>
 <MEAN>   1.40129846E-45 </MEAN>
 <STDV>   1.40129846E-45 </STDV>
 <BIAS>  0.343103081     </BIAS>
 <RMSE>  0.953003407     </RMSE>
 <CORR>   1.40129846E-45 </CORR>
 </EXP>
 </STATION>
 <STATION>
 <MEAN_OBS>   3.71568918     </MEAN_OBS>
 <STDV_OBS>   1.21415544     </STDV_OBS>
 <EXP>
 <ID>        1116 </ID>
 <NAME>REF</NAME>
 <NUM>        3194 </NUM>
 <MEAN>   3.56938291     </MEAN>
 <STDV>   5.66107716E-11 </STDV>
 <BIAS>  0.383988887     </BIAS>
 <RMSE>  0.951656222     </RMSE>
 <CORR>  -6.42552866E-20 </CORR>
 </EXP>
 <EXP>
 <ID>        1116 </ID>
 <NAME>SCATT</NAME>
 <NUM>        3194 </NUM>
 <MEAN>   1.40129846E-45 </MEAN>
 <STDV>   1.40129846E-45 </STDV>
 <BIAS>  0.364323288     </BIAS>
 <RMSE>  0.954404652     </RMSE>
 <CORR>   0.00000000     </CORR>
 </EXP>
 </STATION>
 <STATION>
 <MEAN_OBS>   3.30683517     </MEAN_OBS>
 <STDV_OBS>   1.25712752     </STDV_OBS>
 <EXP>
 <ID>        1162 </ID>
 <NAME>REF</NAME>
 <NUM>        3187 </NUM>
 <MEAN>   3.36941242     </MEAN>
 <STDV> -0.317637920     </STDV>
 <BIAS>  0.358677387     </BIAS>
 <RMSE>  0.960012376     </RMSE>
 <CORR>   5.65683611E-11 </CORR>
 </EXP>
 <EXP>
 <ID>        1162 </ID>
 <NAME>SCATT</NAME>
 <NUM>        3187 </NUM>
 <MEAN>   1.40129846E-45 </MEAN>
 <STDV>   1.40129846E-45 </STDV>
 <BIAS>  0.367729455     </BIAS>
 <RMSE>  0.956921279     </RMSE>
 <CORR>   1.40129846E-45 </CORR>
 </EXP>
 </STATION>
 <STATION>
 <MEAN_OBS>   2.63521647     </MEAN_OBS>
 <STDV_OBS>   1.03023362     </STDV_OBS>
 <EXP>
 <ID>        1099 </ID>
 <NAME>REF</NAME>
 <NUM>        3194 </NUM>
 <MEAN>   2.55737901     </MEAN>
 <STDV>   5.66106606E-11 </STDV>
 <BIAS>  0.366051525     </BIAS>
 <RMSE>  0.932714880     </RMSE>
 <CORR>  -6.42552866E-20 </CORR>
 </EXP>
 <EXP>
 <ID>        1099 </ID>
 <NAME>SCATT</NAME>
 <NUM>        3194 </NUM>
 <MEAN>   1.40129846E-45 </MEAN>
 <STDV>   1.40129846E-45 </STDV>
 <BIAS>  0.337143213     </BIAS>
 <RMSE>  0.945022643     </RMSE>
 <CORR>   0.00000000     </CORR>
 </EXP>
 </STATION>
 <STATION>
 <MEAN_OBS>   3.00943327     </MEAN_OBS>
 <STDV_OBS>   1.10610867     </STDV_OBS>
 <EXP>
 <ID>        1055 </ID>
 <NAME>REF</NAME>
 <NUM>        3194 </NUM>
 <MEAN>   2.85094190     </MEAN>
 <STDV>   5.65684721E-11 </STDV>
 <BIAS>  0.381354302     </BIAS>
 <RMSE>  0.938097715     </RMSE>
 <CORR>   5.65693603E-11 </CORR>
 </EXP>
 <EXP>
 <ID>        1055 </ID>
 <NAME>SCATT</NAME>
 <NUM>        3194 </NUM>
 <MEAN>   1.40129846E-45 </MEAN>
 <STDV>   1.40129846E-45 </STDV>
 <BIAS>  0.375442326     </BIAS>
 <RMSE>  0.940641522     </RMSE>
 <CORR>   1.40129846E-45 </CORR>
 </EXP>
 </STATION>
 <STATION>
 <MEAN_OBS>   3.44416881     </MEAN_OBS>
 <STDV_OBS>   1.24119329     </STDV_OBS>
 <EXP>
 <ID>        1152 </ID>
 <NAME>REF</NAME>
 <NUM>        3194 </NUM>
 <MEAN>   3.43925691     </MEAN>
 <STDV>   5.65999470E-11 </STDV>
 <BIAS>  0.331982791     </BIAS>
 <RMSE>  0.962994695     </RMSE>
 <CORR>   5.65683611E-11 </CORR>
 </EXP>
 <EXP>
 <ID>        1152 </ID>
 <NAME>SCATT</NAME>
 <NUM>        3194 </NUM>
 <MEAN>   1.40129846E-45 </MEAN>
 <STDV>   1.40129846E-45 </STDV>
 <BIAS>  0.329561681     </BIAS>
 <RMSE>  0.964145005     </RMSE>
 <CORR>   1.40129846E-45 </CORR>
 </EXP>
 </STATION>
 <STATION>
 <MEAN_OBS>   3.28869319     </MEAN_OBS>
 <STDV_OBS>   1.25314128     </STDV_OBS>
 <EXP>
 <ID>        1010 </ID>
 <NAME>REF</NAME>
 <NUM>        3194 </NUM>
 <MEAN>   3.32015014     </MEAN>
 <STDV>   5.65694713E-11 </STDV>
 <BIAS>  0.374626935     </BIAS>
 <RMSE>  0.955036938     </RMSE>
 <CORR>  -6.42552866E-20 </CORR>
 </EXP>
 <EXP>
 <ID>        1010 </ID>
 <NAME>SCATT</NAME>
 <NUM>        3194 </NUM>
 <MEAN>   1.40129846E-45 </MEAN>
 <STDV>   1.40129846E-45 </STDV>
 <BIAS>  0.368209094     </BIAS>
 <RMSE>  0.955837250     </RMSE>
 <CORR>   0.00000000     </CORR>
 </EXP>
 </STATION>
 <STATION>
 <MEAN_OBS>   2.16556144     </MEAN_OBS>
 <STDV_OBS>   1.04630268     </STDV_OBS>
 <EXP>
 <ID>        1049 </ID>
 <NAME>REF</NAME>
 <NUM>        3194 </NUM>
 <MEAN>   2.26176095     </MEAN>
 <STDV>   5.66107716E-11 </STDV>
 <BIAS>  0.363712221     </BIAS>
 <RMSE>  0.937012851     </RMSE>
 <CORR>   5.65693603E-11 </CORR>
 </EXP>
 <EXP>
 <ID>        1049 </ID>
 <NAME>SCATT</NAME>
 <NUM>        3194 </NUM>
 <MEAN>   1.40129846E-45 </MEAN>
 <STDV>   1.40129846E-45 </STDV>
 <BIAS>  0.360967815     </BIAS>
 <RMSE>  0.938924909     </RMSE>
 <CORR>   1.40129846E-45 </CORR>
 </EXP>
 </STATION>
 <STATION>
 <MEAN_OBS>   2.57878613     </MEAN_OBS>
 <STDV_OBS>   1.10551465     </STDV_OBS>
 <EXP>
 <ID>        1078 </ID>
 <NAME>REF</NAME>
 <NUM>        3194 </NUM>
 <MEAN>   2.53446269     </MEAN>
 <STDV>   5.65998359E-11 </STDV>
 <BIAS>  0.354886353     </BIAS>
 <RMSE>  0.946825206     </RMSE>
 <CORR>   5.65683611E-11 </CORR>
 </EXP>
 <EXP>
 <ID>        1078 </ID>
 <NAME>SCATT</NAME>
 <NUM>        3194 </NUM>
 <MEAN>   1.40129846E-45 </MEAN>
 <STDV>   1.40129846E-45 </STDV>
 <BIAS>  0.355687499     </BIAS>
 <RMSE>  0.946875513     </RMSE>
 <CORR>   1.40129846E-45 </CORR>
 </EXP>
 </STATION>
 <STATION>
 <MEAN_OBS>   1.11499751     </MEAN_OBS>
 <STDV_OBS>  0.463474482     </STDV_OBS>
 <EXP>
 <ID>       20107 </ID>
 <NAME>REF</NAME>
 <NUM>        1172 </NUM>
 <MEAN>   1.07072592     </MEAN>
 <STDV> -0.317637920     </STDV>
 <BIAS>  0.259697229     </BIAS>
 <RMSE>  0.827269197     </RMSE>
 <CORR>  -6.42552866E-20 </CORR>
 </EXP>
 <EXP>
 <ID>       20107 </ID>
 <NAME>SCATT</NAME>
 <NUM>        1172 </NUM>
 <MEAN>   1.40129846E-45 </MEAN>
 <STDV>   1.40129846E-45 </STDV>
 <BIAS>  0.257425964     </BIAS>
 <RMSE>  0.831408739     </RMSE>
 <CORR>   0.00000000     </CORR>
 </EXP>
 </STATION>
 <STATION>
 <MEAN_OBS>   2.68278098     </MEAN_OBS>
 <STDV_OBS>  0.963908136     </STDV_OBS>
 <EXP>
 <ID>       22003 </ID>
 <NAME>REF</NAME>
 <NUM>        1172 </NUM>
 <MEAN>   2.62563038     </MEAN>
 <STDV>   5.65683611E-11 </STDV>
 <BIAS>  0.366578847     </BIAS>
 <RMSE>  0.927034616     </RMSE>
 <CORR>   5.65693603E-11 </CORR>
 </EXP>
 <EXP>
 <ID>       22003 </ID>
 <NAME>SCATT</NAME>
 <NUM>        1172 </NUM>
 <MEAN>   1.40129846E-45 </MEAN>
 <STDV>   1.40129846E-45 </STDV>
 <BIAS>  0.324899048     </BIAS>
 <RMSE>  0.941729426     </RMSE>
 <CORR>   1.40129846E-45 </CORR>
 </EXP>
 </STATION>
 <STATION>
 <MEAN_OBS>   2.00603294     </MEAN_OBS>
 <STDV_OBS>   1.13948143     </STDV_OBS>
 <EXP>
 <ID>       22004 </ID>
 <NAME>REF</NAME>
 <NUM>        1172 </NUM>
 <MEAN>   2.06357574     </MEAN>
 <STDV>  -6.42552866E-20 </STDV>
 <BIAS>  0.318184316     </BIAS>
 <RMSE>  0.960605502     </RMSE>
 <CORR>   5.66106606E-11 </CORR>
 </EXP>
 <EXP>
 <ID>       22004 </ID>
 <NAME>SCATT</NAME>
 <NUM>        1172 </NUM>
 <MEAN>   1.40129846E-45 </MEAN>
 <STDV>   0.00000000     </STDV>
 <BIAS>  0.311820060     </BIAS>
 <RMSE>  0.962214887     </RMSE>
 <CORR>   1.40129846E-45 </CORR>
 </EXP>
 </STATION>
 <STATION>
 <MEAN_OBS>   2.10342407     </MEAN_OBS>
 <STDV_OBS>   1.00114405     </STDV_OBS>
 <EXP>
 <ID>       22113 </ID>
 <NAME>REF</NAME>
 <NUM>        1172 </NUM>
 <MEAN>   2.37857437     </MEAN>
 <STDV>   5.65693603E-11 </STDV>
 <BIAS>  0.322456449     </BIAS>
 <RMSE>  0.954107344     </RMSE>
 <CORR>   5.65684721E-11 </CORR>
 </EXP>
 <EXP>
 <ID>       22113 </ID>
 <NAME>SCATT</NAME>
 <NUM>        1172 </NUM>
 <MEAN>   1.40129846E-45 </MEAN>
 <STDV>   1.40129846E-45 </STDV>
 <BIAS>  0.334203124     </BIAS>
 <RMSE>  0.950680792     </RMSE>
 <CORR>   1.40129846E-45 </CORR>
 </EXP>
 </STATION>
 <STATION>
 <MEAN_OBS>   2.00179720     </MEAN_OBS>
 <STDV_OBS>   1.10475063     </STDV_OBS>
 <EXP>
 <ID>       22212 </ID>
 <NAME>REF</NAME>
 <NUM>        1172 </NUM>
 <MEAN>   2.09044909     </MEAN>
 <STDV>   5.66106606E-11 </STDV>
 <BIAS>  0.254638553     </BIAS>
 <RMSE>  0.973642886     </RMSE>
 <CORR>   5.65999470E-11 </CORR>
 </EXP>
 <EXP>
 <ID>       22212 </ID>
 <NAME>SCATT</NAME>
 <NUM>        1172 </NUM>
 <MEAN>   1.40129846E-45 </MEAN>
 <STDV>   1.40129846E-45 </STDV>
 <BIAS>  0.255179793     </BIAS>
 <RMSE>  0.973406792     </RMSE>
 <CORR>   1.40129846E-45 </CORR>
 </EXP>
 </STATION>
 <STATION>
 <MEAN_OBS>   1.39984703     </MEAN_OBS>
 <STDV_OBS>  0.552567899     </STDV_OBS>
 <EXP>
 <ID>       20744 </ID>
 <NAME>REF</NAME>
 <NUM>        1128 </NUM>
 <MEAN>   1.46017754     </MEAN>
 <STDV>   5.65684721E-11 </STDV>
 <BIAS>  0.283840179     </BIAS>
 <RMSE>  0.866536856     </RMSE>
 <CORR>   5.65694713E-11 </CORR>
 </EXP>
 <EXP>
 <ID>       20744 </ID>
 <NAME>SCATT</NAME>
 <NUM>        1128 </NUM>
 <MEAN>   1.40129846E-45 </MEAN>
 <STDV>   1.40129846E-45 </STDV>
 <BIAS>  0.255187571     </BIAS>
 <RMSE>  0.890712500     </RMSE>
 <CORR>   1.40129846E-45 </CORR>
 </EXP>
 </STATION>
 <STATION>
 <MEAN_OBS>   2.45752645     </MEAN_OBS>
 <STDV_OBS>  0.909127057     </STDV_OBS>
 <EXP>
 <ID>       22028 </ID>
 <NAME>REF</NAME>
 <NUM>        1172 </NUM>
 <MEAN>   2.51656771     </MEAN>
 <STDV>   5.65998359E-11 </STDV>
 <BIAS>  0.337679386     </BIAS>
 <RMSE>  0.934642315     </RMSE>
 <CORR>   5.66107716E-11 </CORR>
 </EXP>
 <EXP>
 <ID>       22028 </ID>
 <NAME>SCATT</NAME>
 <NUM>        1172 </NUM>
 <MEAN>   1.40129846E-45 </MEAN>
 <STDV>   1.40129846E-45 </STDV>
 <BIAS>  0.328530252     </BIAS>
 <RMSE>  0.938130021     </RMSE>
 <CORR>   1.40129846E-45 </CORR>
 </EXP>
 </STATION>
 <STATION>
 <MEAN_OBS>   1.93329525     </MEAN_OBS>
 <STDV_OBS>   1.09788752     </STDV_OBS>
 <EXP>
 <ID>       22106 </ID>
 <NAME>REF</NAME>
 <NUM>        1157 </NUM>
 <MEAN>   2.05151272     </MEAN>
 <STDV>   5.65694713E-11 </STDV>
 <BIAS>  0.350725502     </BIAS>
 <RMSE>  0.956425905     </RMSE>
 <CORR>   5.65999470E-11 </CORR>
 </EXP>
 <EXP>
 <ID>       22106 </ID>
 <NAME>SCATT</NAME>
 <NUM>        1157 </NUM>
 <MEAN>   1.40129846E-45 </MEAN>
 <STDV>   1.40129846E-45 </STDV>
 <BIAS>  0.347966045     </BIAS>
 <RMSE>  0.957303286     </RMSE>
 <CORR>   1.40129846E-45 </CORR>
 </EXP>
 </STATION>
 <STATION>
 <MEAN_OBS>   2.56796503     </MEAN_OBS>
 <STDV_OBS>   1.22765756     </STDV_OBS>
 <EXP>
 <ID>        1114 </ID>
 <NAME>REF</NAME>
 <NUM>        2882 </NUM>
 <MEAN>   3.26091075     </MEAN>
 <STDV>  -6.42552866E-20 </STDV>
 <BIAS>  0.515865684     </BIAS>
 <RMSE>  0.913514674     </RMSE>
 <CORR>   5.65683611E-11 </CORR>
 </EXP>
 <EXP>
 <ID>        1114 </ID>
 <NAME>SCATT</NAME>
 <NUM>        2882 </NUM>
 <MEAN>   1.40129846E-45 </MEAN>
 <STDV>   0.00000000     </STDV>
 <BIAS>  0.509495616     </BIAS>
 <RMSE>  0.915351272     </RMSE>
 <CORR>   1.40129846E-45 </CORR>
 </EXP>
 </STATION>
 <STATION>
 <MEAN_OBS>   3.55324101     </MEAN_OBS>
 <STDV_OBS>   1.31620800     </STDV_OBS>
 <EXP>
 <ID>        1141 </ID>
 <NAME>REF</NAME>
 <NUM>        3194 </NUM>
 <MEAN>   3.48791647     </MEAN>
 <STDV>   5.65693603E-11 </STDV>
 <BIAS>  0.387920529     </BIAS>
 <RMSE>  0.955833256     </RMSE>
 <CORR>   5.65999470E-11 </CORR>
 </EXP>
 <EXP>
 <ID>        1141 </ID>
 <NAME>SCATT</NAME>
 <NUM>        3194 </NUM>
 <MEAN>   1.40129846E-45 </MEAN>
 <STDV>   1.40129846E-45 </STDV>
 <BIAS>  0.395449609     </BIAS>
 <RMSE>  0.954158247     </RMSE>
 <CORR>   1.40129846E-45 </CORR>
 </EXP>
 </STATION>
 <STATION>
 <MEAN_OBS>   1.75587070     </MEAN_OBS>
 <STDV_OBS>   1.14090943     </STDV_OBS>
 <EXP>
 <ID>        1082 </ID>
 <NAME>REF</NAME>
 <NUM>        3118 </NUM>
 <MEAN>   1.91099179     </MEAN>
 <STDV>   5.66106606E-11 </STDV>
 <BIAS>  0.476685405     </BIAS>
 <RMSE>  0.917421401     </RMSE>
 <CORR> -0.317637920     </CORR>
 </EXP>
 <EXP>
 <ID>        1082 </ID>
 <NAME>SCATT</NAME>
 <NUM>        3118 </NUM>
 <MEAN>   1.40129846E-45 </MEAN>
 <STDV>   1.40129846E-45 </STDV>
 <BIAS>  0.469837457     </BIAS>
 <RMSE>  0.920089722     </RMSE>
 <CORR>   1.40129846E-45 </CORR>
 </EXP>
 </STATION>
 <STATION>
 <MEAN_OBS>   3.20290971     </MEAN_OBS>
 <STDV_OBS>   1.30772805     </STDV_OBS>
 <EXP>
 <ID>        1183 </ID>
 <NAME>REF</NAME>
 <NUM>        3068 </NUM>
 <MEAN>   3.18171835     </MEAN>
 <STDV>  -6.42552866E-20 </STDV>
 <BIAS>  0.329516143     </BIAS>
 <RMSE>  0.968533814     </RMSE>
 <CORR>   5.66107716E-11 </CORR>
 </EXP>
 <EXP>
 <ID>        1183 </ID>
 <NAME>SCATT</NAME>
 <NUM>        3068 </NUM>
 <MEAN>   1.40129846E-45 </MEAN>
 <STDV>   0.00000000     </STDV>
 <BIAS>  0.334965587     </BIAS>
 <RMSE>  0.967759013     </RMSE>
 <CORR>   1.40129846E-45 </CORR>
 </EXP>
 </STATION>
 <STATION>
 <MEAN_OBS>   2.07980084     </MEAN_OBS>
 <STDV_OBS>   1.11962748     </STDV_OBS>
 <EXP>
 <ID>        1089 </ID>
 <NAME>REF</NAME>
 <NUM>        3180 </NUM>
 <MEAN>   2.21337295     </MEAN>
 <STDV>   5.65693603E-11 </STDV>
 <BIAS>  0.344408393     </BIAS>
 <RMSE>  0.951997519     </RMSE>
 <CORR> -0.317637920     </CORR>
 </EXP>
 <EXP>
 <ID>        1089 </ID>
 <NAME>SCATT</NAME>
 <NUM>        3180 </NUM>
 <MEAN>   1.40129846E-45 </MEAN>
 <STDV>   1.40129846E-45 </STDV>
 <BIAS>  0.343866169     </BIAS>
 <RMSE>  0.952265799     </RMSE>
 <CORR>   1.40129846E-45 </CORR>
 </EXP>
 </STATION>
 <STATION>
 <MEAN_OBS>   2.70067716     </MEAN_OBS>
 <STDV_OBS>   1.09602523     </STDV_OBS>
 <EXP>
 <ID>        1052 </ID>
 <NAME>REF</NAME>
 <NUM>        3194 </NUM>
 <MEAN>   2.60662842     </MEAN>
 <STDV>   5.66106606E-11 </STDV>
 <BIAS>  0.372140646     </BIAS>
 <RMSE>  0.939948201     </RMSE>
 <CORR>   5.65694713E-11 </CORR>
 </EXP>
 <EXP>
 <ID>        1052 </ID>
 <NAME>SCATT</NAME>
 <NUM>        3194 </NUM>
 <MEAN>   1.40129846E-45 </MEAN>
 <STDV>   1.40129846E-45 </STDV>
 <BIAS>  0.360553414     </BIAS>
 <RMSE>  0.944324553     </RMSE>
 <CORR>   1.40129846E-45 </CORR>
 </EXP>
 </STATION>
 <STATION>
 <MEAN_OBS>   2.96809077     </MEAN_OBS>
 <STDV_OBS>   1.17269838     </STDV_OBS>
 <EXP>
 <ID>        1169 </ID>
 <NAME>REF</NAME>
 <NUM>        3188 </NUM>
 <MEAN>   2.81596327     </MEAN>
 <STDV>   5.65999470E-11 </STDV>
 <BIAS>  0.336505324     </BIAS>
 <RMSE>  0.959553838     </RMSE>
 <CORR>   5.66107716E-11 </CORR>
 </EXP>
 <EXP>
 <ID>        1169 </ID>
 <NAME>SCATT</NAME>
 <NUM>        3188 </NUM>
 <MEAN>   1.40129846E-45 </MEAN>
 <STDV>   1.40129846E-45 </STDV>
 <BIAS>  0.329418242     </BIAS>
 <RMSE>  0.961383879     </RMSE>
 <CORR>   1.40129846E-45 </CORR>
 </EXP>
 </STATION>
 <STATION>
 <MEAN_OBS>   2.88202906     </MEAN_OBS>
 <STDV_OBS>  0.864917874     </STDV_OBS>
 <EXP>
 <ID>        2267 </ID>
 <NAME>REF</NAME>
 <NUM>        3186 </NUM>
 <MEAN>   2.83893538     </MEAN>
 <STDV>   5.65683611E-11 </STDV>
 <BIAS>  0.333196223     </BIAS>
 <RMSE>  0.947570145     </RMSE>
 <CORR>   5.65998359E-11 </CORR>
 </EXP>
 <EXP>
 <ID>        2267 </ID>
 <NAME>SCATT</NAME>
 <NUM>        3186 </NUM>
 <MEAN>   1.40129846E-45 </MEAN>
 <STDV>   1.40129846E-45 </STDV>
 <BIAS>  0.332850456     </BIAS>
 <RMSE>  0.947571456     </RMSE>
 <CORR>   1.40129846E-45 </CORR>
 </EXP>
 </STATION>
 <STATION>
 <MEAN_OBS>   2.40476418     </MEAN_OBS>
 <STDV_OBS>  0.961722255     </STDV_OBS>
 <EXP>
 <ID>        2271 </ID>
 <NAME>REF</NAME>
 <NUM>        3180 </NUM>
 <MEAN>   2.53438592     </MEAN>
 <STDV>  -6.42552866E-20 </STDV>
 <BIAS>  0.291412681     </BIAS>
 <RMSE>  0.973962724     </RMSE>
 <CORR> -0.317637920     </CORR>
 </EXP>
 <EXP>
 <ID>        2271 </ID>
 <NAME>SCATT</NAME>
 <NUM>        3180 </NUM>
 <MEAN>   1.40129846E-45 </MEAN>
 <STDV>   0.00000000     </STDV>
 <BIAS>  0.289614886     </BIAS>
 <RMSE>  0.973966122     </RMSE>
 <CORR>   1.40129846E-45 </CORR>
 </EXP>
 </STATION>
 <STATION>
 <MEAN_OBS>   3.05356193     </MEAN_OBS>
 <STDV_OBS>  0.923633039     </STDV_OBS>
 <EXP>
 <ID>        2284 </ID>
 <NAME>REF</NAME>
 <NUM>        3182 </NUM>
 <MEAN>   3.17738414     </MEAN>
 <STDV>   5.66106606E-11 </STDV>
 <BIAS>  0.319258690     </BIAS>
 <RMSE>  0.956104219     </RMSE>
 <CORR>   5.65693603E-11 </CORR>
 </EXP>
 <EXP>
 <ID>        2284 </ID>
 <NAME>SCATT</NAME>
 <NUM>        3182 </NUM>
 <MEAN>   1.40129846E-45 </MEAN>
 <STDV>   1.40129846E-45 </STDV>
 <BIAS>  0.320349097     </BIAS>
 <RMSE>  0.955658793     </RMSE>
 <CORR>   1.40129846E-45 </CORR>
 </EXP>
 </STATION>
 <STATION>
 <MEAN_OBS>   2.82184815     </MEAN_OBS>
 <STDV_OBS>  0.920727372     </STDV_OBS>
 <EXP>
 <ID>        2286 </ID>
 <NAME>REF</NAME>
 <NUM>        3194 </NUM>
 <MEAN>   2.90198112     </MEAN>
 <STDV>   5.65999470E-11 </STDV>
 <BIAS>  0.338194847     </BIAS>
 <RMSE>  0.956307173     </RMSE>
 <CORR> -0.317637920     </CORR>
 </EXP>
 <EXP>
 <ID>        2286 </ID>
 <NAME>SCATT</NAME>
 <NUM>        3194 </NUM>
 <MEAN>   1.40129846E-45 </MEAN>
 <STDV>   1.40129846E-45 </STDV>
 <BIAS>  0.338092148     </BIAS>
 <RMSE>  0.956191897     </RMSE>
 <CORR>   1.40129846E-45 </CORR>
 </EXP>
 </STATION>
 <STATION>
 <MEAN_OBS>   3.32364321     </MEAN_OBS>
 <STDV_OBS>  0.927562475     </STDV_OBS>
 <EXP>
 <ID>        2287 </ID>
 <NAME>REF</NAME>
 <NUM>        3156 </NUM>
 <MEAN>   3.18103099     </MEAN>
 <STDV>   5.65694713E-11 </STDV>
 <BIAS>  0.221536145     </BIAS>
 <RMSE>  0.972015202     </RMSE>
 <CORR>   5.65998359E-11 </CORR>
 </EXP>
 <EXP>
 <ID>        2287 </ID>
 <NAME>SCATT</NAME>
 <NUM>        3156 </NUM>
 <MEAN>   1.40129846E-45 </MEAN>
 <STDV>   1.40129846E-45 </STDV>
 <BIAS>  0.225478619     </BIAS>
 <RMSE>  0.971032143     </RMSE>
 <CORR>   1.40129846E-45 </CORR>
 </EXP>
 </STATION>
 <STATION>
 <MEAN_OBS>   2.58841801     </MEAN_OBS>
 <STDV_OBS>  0.960706353     </STDV_OBS>
 <EXP>
 <ID>        2293 </ID>
 <NAME>REF</NAME>
 <NUM>        3194 </NUM>
 <MEAN>   2.72463965     </MEAN>
 <STDV>   5.65683611E-11 </STDV>
 <BIAS>  0.309277117     </BIAS>
 <RMSE>  0.963627338     </RMSE>
 <CORR>   5.65693603E-11 </CORR>
 </EXP>
 <EXP>
 <ID>        2293 </ID>
 <NAME>SCATT</NAME>
 <NUM>        3194 </NUM>
 <MEAN>   1.40129846E-45 </MEAN>
 <STDV>   1.40129846E-45 </STDV>
 <BIAS>  0.310925156     </BIAS>
 <RMSE>  0.962852120     </RMSE>
 <CORR>   1.40129846E-45 </CORR>
 </EXP>
 </STATION>
 <STATION>
 <MEAN_OBS>   3.04599929     </MEAN_OBS>
 <STDV_OBS>  0.891594112     </STDV_OBS>
 <EXP>
 <ID>        2297 </ID>
 <NAME>REF</NAME>
 <NUM>        3181 </NUM>
 <MEAN>   3.04206181     </MEAN>
 <STDV>   5.65684721E-11 </STDV>
 <BIAS>  0.279418975     </BIAS>
 <RMSE>  0.958500743     </RMSE>
 <CORR> -0.317637920     </CORR>
 </EXP>
 <EXP>
 <ID>        2297 </ID>
 <NAME>SCATT</NAME>
 <NUM>        3181 </NUM>
 <MEAN>   0.00000000     </MEAN>
 <STDV>   1.40129846E-45 </STDV>
 <BIAS>  0.280992895     </BIAS>
 <RMSE>  0.958064735     </RMSE>
 <CORR>   1.40129846E-45 </CORR>
 </EXP>
 </STATION>
 <STATION>
 <MEAN_OBS>   2.53939033     </MEAN_OBS>
 <STDV_OBS>   1.12119603     </STDV_OBS>
 <EXP>
 <ID>        2013 </ID>
 <NAME>REF</NAME>
 <NUM>        3182 </NUM>
 <MEAN>   2.48646927     </MEAN>
 <STDV>  -6.42552866E-20 </STDV>
 <BIAS>  0.277636200     </BIAS>
 <RMSE>  0.969626844     </RMSE>
 <CORR>   5.65998359E-11 </CORR>
 </EXP>
 <EXP>
 <ID>        2013 </ID>
 <NAME>SCATT</NAME>
 <NUM>        3182 </NUM>
 <MEAN>   1.40129846E-45 </MEAN>
 <STDV>   0.00000000     </STDV>
 <BIAS>  0.274721950     </BIAS>
 <RMSE>  0.970240772     </RMSE>
 <CORR>   1.40129846E-45 </CORR>
 </EXP>
 </STATION>
 <STATION>
 <MEAN_OBS>   2.32904434     </MEAN_OBS>
 <STDV_OBS>   1.17129636     </STDV_OBS>
 <EXP>
 <ID>        2019 </ID>
 <NAME>REF</NAME>
 <NUM>        3167 </NUM>
 <MEAN>   2.42185950     </MEAN>
 <STDV> -0.317637920     </STDV>
 <BIAS>  0.318117350     </BIAS>
 <RMSE>  0.962980449     </RMSE>
 <CORR>   5.65693603E-11 </CORR>
 </EXP>
 <EXP>
 <ID>        2019 </ID>
 <NAME>SCATT</NAME>
 <NUM>        3167 </NUM>
 <MEAN>   1.40129846E-45 </MEAN>
 <STDV>   1.40129846E-45 </STDV>
 <BIAS>  0.320308000     </BIAS>
 <RMSE>  0.962570131     </RMSE>
 <CORR>   1.40129846E-45 </CORR>
 </EXP>
 </STATION>
 <STATION>
 <MEAN_OBS>   1.94213843     </MEAN_OBS>
 <STDV_OBS>   1.02225256     </STDV_OBS>
 <EXP>
 <ID>        2029 </ID>
 <NAME>REF</NAME>
 <NUM>        3182 </NUM>
 <MEAN>   1.85814238     </MEAN>
 <STDV>   5.65693603E-11 </STDV>
 <BIAS>  0.286724627     </BIAS>
 <RMSE>  0.959682345     </RMSE>
 <CORR>   5.66106606E-11 </CORR>
 </EXP>
 <EXP>
 <ID>        2029 </ID>
 <NAME>SCATT</NAME>
 <NUM>        3182 </NUM>
 <MEAN>   1.40129846E-45 </MEAN>
 <STDV>   1.40129846E-45 </STDV>
 <BIAS>  0.287824333     </BIAS>
 <RMSE>  0.959695995     </RMSE>
 <CORR>   1.40129846E-45 </CORR>
 </EXP>
 </STATION>
 <STATION>
 <MEAN_OBS>   1.40447938     </MEAN_OBS>
 <STDV_OBS>   1.05817831     </STDV_OBS>
 <EXP>
 <ID>        2036 </ID>
 <NAME>REF</NAME>
 <NUM>        3166 </NUM>
 <MEAN>   2.09995008     </MEAN>
 <STDV>   5.66106606E-11 </STDV>
 <BIAS>  0.402750164     </BIAS>
 <RMSE>  0.925173283     </RMSE>
 <CORR>   5.65694713E-11 </CORR>
 </EXP>
 <EXP>
 <ID>        2036 </ID>
 <NAME>SCATT</NAME>
 <NUM>        3166 </NUM>
 <MEAN>   1.40129846E-45 </MEAN>
 <STDV>   1.40129846E-45 </STDV>
 <BIAS>  0.396074057     </BIAS>
 <RMSE>  0.927337170     </RMSE>
 <CORR>   1.40129846E-45 </CORR>
 </EXP>
 </STATION>
 <STATION>
 <MEAN_OBS>   2.03674054     </MEAN_OBS>
 <STDV_OBS>   1.05625355     </STDV_OBS>
 <EXP>
 <ID>        2044 </ID>
 <NAME>REF</NAME>
 <NUM>        3181 </NUM>
 <MEAN>   2.05495715     </MEAN>
 <STDV>   5.65694713E-11 </STDV>
 <BIAS>  0.332687736     </BIAS>
 <RMSE>  0.950644314     </RMSE>
 <CORR>   5.65999470E-11 </CORR>
 </EXP>
 <EXP>
 <ID>        2044 </ID>
 <NAME>SCATT</NAME>
 <NUM>        3181 </NUM>
 <MEAN>   1.40129846E-45 </MEAN>
 <STDV>   1.40129846E-45 </STDV>
 <BIAS>  0.339829594     </BIAS>
 <RMSE>  0.948677182     </RMSE>
 <CORR>   1.40129846E-45 </CORR>
 </EXP>
 </STATION>
 <STATION>
 <MEAN_OBS>   1.94157076     </MEAN_OBS>
 <STDV_OBS>   1.07467020     </STDV_OBS>
 <EXP>
 <ID>        2049 </ID>
 <NAME>REF</NAME>
 <NUM>        3181 </NUM>
 <MEAN>   2.12298274     </MEAN>
 <STDV> -0.317637920     </STDV>
 <BIAS>  0.343722433     </BIAS>
 <RMSE>  0.947990000     </RMSE>
 <CORR>  -6.42552866E-20 </CORR>
 </EXP>
 <EXP>
 <ID>        2049 </ID>
 <NAME>SCATT</NAME>
 <NUM>        3181 </NUM>
 <MEAN>   1.40129846E-45 </MEAN>
 <STDV>   1.40129846E-45 </STDV>
 <BIAS>  0.341674119     </BIAS>
 <RMSE>  0.948820710     </RMSE>
 <CORR>   0.00000000     </CORR>
 </EXP>
 </STATION>
 <STATION>
 <MEAN_OBS>   1.84934175     </MEAN_OBS>
 <STDV_OBS>   1.05655456     </STDV_OBS>
 <EXP>
 <ID>        2072 </ID>
 <NAME>REF</NAME>
 <NUM>        3182 </NUM>
 <MEAN>   1.98838782     </MEAN>
 <STDV>   5.65683611E-11 </STDV>
 <BIAS>  0.387746185     </BIAS>
 <RMSE>  0.931035519     </RMSE>
 <CORR>  -6.42552866E-20 </CORR>
 </EXP>
 <EXP>
 <ID>        2072 </ID>
 <NAME>SCATT</NAME>
 <NUM>        3182 </NUM>
 <MEAN>   1.40129846E-45 </MEAN>
 <STDV>   1.40129846E-45 </STDV>
 <BIAS>  0.363755018     </BIAS>
 <RMSE>  0.939314544     </RMSE>
 <CORR>   0.00000000     </CORR>
 </EXP>
 </STATION>
 <STATION>
 <MEAN_OBS>   1.57092834     </MEAN_OBS>
 <STDV_OBS>   1.10504651     </STDV_OBS>
 <EXP>
 <ID>        2081 </ID>
 <NAME>REF</NAME>
 <NUM>        3175 </NUM>
 <MEAN>   1.82343030     </MEAN>
 <STDV>   5.66106606E-11 </STDV>
 <BIAS>  0.426273376     </BIAS>
 <RMSE>  0.926101506     </RMSE>
 <CORR>   5.66107716E-11 </CORR>
 </EXP>
 <EXP>
 <ID>        2081 </ID>
 <NAME>SCATT</NAME>
 <NUM>        3175 </NUM>
 <MEAN>   1.40129846E-45 </MEAN>
 <STDV>   1.40129846E-45 </STDV>
 <BIAS>  0.410373271     </BIAS>
 <RMSE>  0.931739450     </RMSE>
 <CORR>   1.40129846E-45 </CORR>
 </EXP>
 </STATION>
 <STATION>
 <MEAN_OBS>   1.89579976     </MEAN_OBS>
 <STDV_OBS>   1.13389277     </STDV_OBS>
 <EXP>
 <ID>        2095 </ID>
 <NAME>REF</NAME>
 <NUM>        3182 </NUM>
 <MEAN>   2.15954709     </MEAN>
 <STDV>  -6.42552866E-20 </STDV>
 <BIAS>  0.506638646     </BIAS>
 <RMSE>  0.901774764     </RMSE>
 <CORR>   5.65998359E-11 </CORR>
 </EXP>
 <EXP>
 <ID>        2095 </ID>
 <NAME>SCATT</NAME>
 <NUM>        3182 </NUM>
 <MEAN>   1.40129846E-45 </MEAN>
 <STDV>   0.00000000     </STDV>
 <BIAS>  0.506700754     </BIAS>
 <RMSE>  0.902071059     </RMSE>
 <CORR>   1.40129846E-45 </CORR>
 </EXP>
 </STATION>
 <STATION>
 <MEAN_OBS>   2.54581594     </MEAN_OBS>
 <STDV_OBS>   1.18444657     </STDV_OBS>
 <EXP>
 <ID>        2101 </ID>
 <NAME>REF</NAME>
 <NUM>        3187 </NUM>
 <MEAN>   2.58143711     </MEAN>
 <STDV>   5.65694713E-11 </STDV>
 <BIAS>  0.454262763     </BIAS>
 <RMSE>  0.951751173     </RMSE>
 <CORR>   5.65684721E-11 </CORR>
 </EXP>
 <EXP>
 <ID>        2101 </ID>
 <NAME>SCATT</NAME>
 <NUM>        3187 </NUM>
 <MEAN>   1.40129846E-45 </MEAN>
 <STDV>   1.40129846E-45 </STDV>
 <BIAS>  0.452959001     </BIAS>
 <RMSE>  0.952577412     </RMSE>
 <CORR>   1.40129846E-45 </CORR>
 </EXP>
 </STATION>
 <STATION>
 <MEAN_OBS>   1.55397654     </MEAN_OBS>
 <STDV_OBS>   1.08664727     </STDV_OBS>
 <EXP>
 <ID>        2119 </ID>
 <NAME>REF</NAME>
 <NUM>        3188 </NUM>
 <MEAN>   2.13442230     </MEAN>
 <STDV>   5.65998359E-11 </STDV>
 <BIAS>  0.461134732     </BIAS>
 <RMSE>  0.905467570     </RMSE>
 <CORR>   5.66107716E-11 </CORR>
 </EXP>
 <EXP>
 <ID>        2119 </ID>
 <NAME>SCATT</NAME>
 <NUM>        3188 </NUM>
 <MEAN>   1.40129846E-45 </MEAN>
 <STDV>   1.40129846E-45 </STDV>
 <BIAS>  0.460456789     </BIAS>
 <RMSE>  0.907570541     </RMSE>
 <CORR>   1.40129846E-45 </CORR>
 </EXP>
 </STATION>
 <STATION>
 <MEAN_OBS>   2.20461822     </MEAN_OBS>
 <STDV_OBS>   1.12870240     </STDV_OBS>
 <EXP>
 <ID>        2121 </ID>
 <NAME>REF</NAME>
 <NUM>        3181 </NUM>
 <MEAN>   2.32898426     </MEAN>
 <STDV>   5.66106606E-11 </STDV>
 <BIAS>  0.368493557     </BIAS>
 <RMSE>  0.963268936     </RMSE>
 <CORR>   5.65683611E-11 </CORR>
 </EXP>
 <EXP>
 <ID>        2121 </ID>
 <NAME>SCATT</NAME>
 <NUM>        3181 </NUM>
 <MEAN>   0.00000000     </MEAN>
 <STDV>   1.40129846E-45 </STDV>
 <BIAS>  0.359909803     </BIAS>
 <RMSE>  0.964792192     </RMSE>
 <CORR>   1.40129846E-45 </CORR>
 </EXP>
 </STATION>
 <STATION>
 <MEAN_OBS>   2.19431996     </MEAN_OBS>
 <STDV_OBS>   1.08246911     </STDV_OBS>
 <EXP>
 <ID>        2124 </ID>
 <NAME>REF</NAME>
 <NUM>        3177 </NUM>
 <MEAN>   2.33466864     </MEAN>
 <STDV>   5.66107716E-11 </STDV>
 <BIAS>  0.299938500     </BIAS>
 <RMSE>  0.966047883     </RMSE>
 <CORR>   5.65684721E-11 </CORR>
 </EXP>
 <EXP>
 <ID>        2124 </ID>
 <NAME>SCATT</NAME>
 <NUM>        3177 </NUM>
 <MEAN>   1.40129846E-45 </MEAN>
 <STDV>   1.40129846E-45 </STDV>
 <BIAS>  0.293630302     </BIAS>
 <RMSE>  0.967534244     </RMSE>
 <CORR>   1.40129846E-45 </CORR>
 </EXP>
 </STATION>
 <STATION>
 <MEAN_OBS>   2.27555871     </MEAN_OBS>
 <STDV_OBS>  0.954697430     </STDV_OBS>
 <EXP>
 <ID>        2126 </ID>
 <NAME>REF</NAME>
 <NUM>        3167 </NUM>
 <MEAN>   2.55044842     </MEAN>
 <STDV>   5.65694713E-11 </STDV>
 <BIAS>  0.369037420     </BIAS>
 <RMSE>  0.953273594     </RMSE>
 <CORR>  -6.42552866E-20 </CORR>
 </EXP>
 <EXP>
 <ID>        2126 </ID>
 <NAME>SCATT</NAME>
 <NUM>        3167 </NUM>
 <MEAN>   1.40129846E-45 </MEAN>
 <STDV>   1.40129846E-45 </STDV>
 <BIAS>  0.362190276     </BIAS>
 <RMSE>  0.955091178     </RMSE>
 <CORR>   0.00000000     </CORR>
 </EXP>
 </STATION>
 <STATION>
 <MEAN_OBS>   2.27135873     </MEAN_OBS>
 <STDV_OBS>   1.12649691     </STDV_OBS>
 <EXP>
 <ID>        2141 </ID>
 <NAME>REF</NAME>
 <NUM>        3194 </NUM>
 <MEAN>   2.09241056     </MEAN>
 <STDV>   5.65999470E-11 </STDV>
 <BIAS>  0.309734553     </BIAS>
 <RMSE>  0.961421728     </RMSE>
 <CORR>   5.65684721E-11 </CORR>
 </EXP>
 <EXP>
 <ID>        2141 </ID>
 <NAME>SCATT</NAME>
 <NUM>        3194 </NUM>
 <MEAN>   1.40129846E-45 </MEAN>
 <STDV>   1.40129846E-45 </STDV>
 <BIAS>  0.312864989     </BIAS>
 <RMSE>  0.960722744     </RMSE>
 <CORR>   1.40129846E-45 </CORR>
 </EXP>
 </STATION>
 <STATION>
 <MEAN_OBS>   2.27460933     </MEAN_OBS>
 <STDV_OBS>   1.14318693     </STDV_OBS>
 <EXP>
 <ID>        2149 </ID>
 <NAME>REF</NAME>
 <NUM>        3113 </NUM>
 <MEAN>   2.26454735     </MEAN>
 <STDV>   5.65684721E-11 </STDV>
 <BIAS>  0.377711564     </BIAS>
 <RMSE>  0.944363713     </RMSE>
 <CORR>   5.65683611E-11 </CORR>
 </EXP>
 <EXP>
 <ID>        2149 </ID>
 <NAME>SCATT</NAME>
 <NUM>        3113 </NUM>
 <MEAN>   1.40129846E-45 </MEAN>
 <STDV>   1.40129846E-45 </STDV>
 <BIAS>  0.377275169     </BIAS>
 <RMSE>  0.944722176     </RMSE>
 <CORR>   1.40129846E-45 </CORR>
 </EXP>
 </STATION>
 <STATION>
 <MEAN_OBS>   2.00494838     </MEAN_OBS>
 <STDV_OBS>   1.03092968     </STDV_OBS>
 <EXP>
 <ID>        2151 </ID>
 <NAME>REF</NAME>
 <NUM>        3180 </NUM>
 <MEAN>   2.29191518     </MEAN>
 <STDV>   5.66106606E-11 </STDV>
 <BIAS>  0.313081741     </BIAS>
 <RMSE>  0.959774792     </RMSE>
 <CORR>   5.65998359E-11 </CORR>
 </EXP>
 <EXP>
 <ID>        2151 </ID>
 <NAME>SCATT</NAME>
 <NUM>        3180 </NUM>
 <MEAN>   1.40129846E-45 </MEAN>
 <STDV>   1.40129846E-45 </STDV>
 <BIAS>  0.313894391     </BIAS>
 <RMSE>  0.959416747     </RMSE>
 <CORR>   1.40129846E-45 </CORR>
 </EXP>
 </STATION>
 <STATION>
 <MEAN_OBS>   2.02758193     </MEAN_OBS>
 <STDV_OBS>   1.11984193     </STDV_OBS>
 <EXP>
 <ID>        2154 </ID>
 <NAME>REF</NAME>
 <NUM>        3194 </NUM>
 <MEAN>   2.27269983     </MEAN>
 <STDV>   5.66107716E-11 </STDV>
 <BIAS>  0.411510497     </BIAS>
 <RMSE>  0.937008739     </RMSE>
 <CORR>  -6.42552866E-20 </CORR>
 </EXP>
 <EXP>
 <ID>        2154 </ID>
 <NAME>SCATT</NAME>
 <NUM>        3194 </NUM>
 <MEAN>   1.40129846E-45 </MEAN>
 <STDV>   1.40129846E-45 </STDV>
 <BIAS>  0.417201102     </BIAS>
 <RMSE>  0.935261011     </RMSE>
 <CORR>   0.00000000     </CORR>
 </EXP>
 </STATION>
 <STATION>
 <MEAN_OBS>   2.21793175     </MEAN_OBS>
 <STDV_OBS>  0.981862724     </STDV_OBS>
 <EXP>
 <ID>        2171 </ID>
 <NAME>REF</NAME>
 <NUM>        3161 </NUM>
 <MEAN>   2.45372272     </MEAN>
 <STDV> -0.317637920     </STDV>
 <BIAS>  0.332815826     </BIAS>
 <RMSE>  0.955329776     </RMSE>
 <CORR>   5.65998359E-11 </CORR>
 </EXP>
 <EXP>
 <ID>        2171 </ID>
 <NAME>SCATT</NAME>
 <NUM>        3161 </NUM>
 <MEAN>   1.40129846E-45 </MEAN>
 <STDV>   1.40129846E-45 </STDV>
 <BIAS>  0.330676705     </BIAS>
 <RMSE>  0.955413580     </RMSE>
 <CORR>   1.40129846E-45 </CORR>
 </EXP>
 </STATION>
 <STATION>
 <MEAN_OBS>   1.63860118     </MEAN_OBS>
 <STDV_OBS>   1.10988772     </STDV_OBS>
 <EXP>
 <ID>        2174 </ID>
 <NAME>REF</NAME>
 <NUM>        3175 </NUM>
 <MEAN>   2.18018699     </MEAN>
 <STDV>   5.65693603E-11 </STDV>
 <BIAS>  0.436303347     </BIAS>
 <RMSE>  0.918550134     </RMSE>
 <CORR>   5.65683611E-11 </CORR>
 </EXP>
 <EXP>
 <ID>        2174 </ID>
 <NAME>SCATT</NAME>
 <NUM>        3175 </NUM>
 <MEAN>   1.40129846E-45 </MEAN>
 <STDV>   1.40129846E-45 </STDV>
 <BIAS>  0.439096808     </BIAS>
 <RMSE>  0.918708205     </RMSE>
 <CORR>   1.40129846E-45 </CORR>
 </EXP>
 </STATION>
 <STATION>
 <MEAN_OBS>   2.24846482     </MEAN_OBS>
 <STDV_OBS>  0.996997952     </STDV_OBS>
 <EXP>
 <ID>        2181 </ID>
 <NAME>REF</NAME>
 <NUM>        3181 </NUM>
 <MEAN>   2.50366592     </MEAN>
 <STDV>   5.66106606E-11 </STDV>
 <BIAS>  0.341883689     </BIAS>
 <RMSE>  0.957005858     </RMSE>
 <CORR>  -6.42552866E-20 </CORR>
 </EXP>
 <EXP>
 <ID>        2181 </ID>
 <NAME>SCATT</NAME>
 <NUM>        3181 </NUM>
 <MEAN>   1.40129846E-45 </MEAN>
 <STDV>   1.40129846E-45 </STDV>
 <BIAS>  0.355043292     </BIAS>
 <RMSE>  0.952596843     </RMSE>
 <CORR>   0.00000000     </CORR>
 </EXP>
 </STATION>
 <STATION>
 <MEAN_OBS>   2.18827367     </MEAN_OBS>
 <STDV_OBS>   1.04015255     </STDV_OBS>
 <EXP>
 <ID>        2184 </ID>
 <NAME>REF</NAME>
 <NUM>        3188 </NUM>
 <MEAN>   2.21367216     </MEAN>
 <STDV>   5.66107716E-11 </STDV>
 <BIAS>  0.282578886     </BIAS>
 <RMSE>  0.964293063     </RMSE>
 <CORR>   5.65683611E-11 </CORR>
 </EXP>
 <EXP>
 <ID>        2184 </ID>
 <NAME>SCATT</NAME>
 <NUM>        3188 </NUM>
 <MEAN>   1.40129846E-45 </MEAN>
 <STDV>   1.40129846E-45 </STDV>
 <BIAS>  0.290340722     </BIAS>
 <RMSE>  0.962324023     </RMSE>
 <CORR>   1.40129846E-45 </CORR>
 </EXP>
 </STATION>
 <STATION>
 <MEAN_OBS>   2.54657269     </MEAN_OBS>
 <STDV_OBS>  0.996807218     </STDV_OBS>
 <EXP>
 <ID>        2186 </ID>
 <NAME>REF</NAME>
 <NUM>        3194 </NUM>
 <MEAN>   2.73218632     </MEAN>
 <STDV>  -6.42552866E-20 </STDV>
 <BIAS>  0.338165462     </BIAS>
 <RMSE>  0.961186111     </RMSE>
 <CORR>   5.65998359E-11 </CORR>
 </EXP>
 <EXP>
 <ID>        2186 </ID>
 <NAME>SCATT</NAME>
 <NUM>        3194 </NUM>
 <MEAN>   1.40129846E-45 </MEAN>
 <STDV>   0.00000000     </STDV>
 <BIAS>  0.338711768     </BIAS>
 <RMSE>  0.960320950     </RMSE>
 <CORR>   1.40129846E-45 </CORR>
 </EXP>
 </STATION>
 <STATION>
 <MEAN_OBS>   2.66878414     </MEAN_OBS>
 <STDV_OBS>   1.06002235     </STDV_OBS>
 <EXP>
 <ID>        2197 </ID>
 <NAME>REF</NAME>
 <NUM>        3188 </NUM>
 <MEAN>   2.76763535     </MEAN>
 <STDV>   5.65693603E-11 </STDV>
 <BIAS>  0.274966091     </BIAS>
 <RMSE>  0.973560750     </RMSE>
 <CORR>   5.65998359E-11 </CORR>
 </EXP>
 <EXP>
 <ID>        2197 </ID>
 <NAME>SCATT</NAME>
 <NUM>        3188 </NUM>
 <MEAN>   1.40129846E-45 </MEAN>
 <STDV>   1.40129846E-45 </STDV>
 <BIAS>  0.280153722     </BIAS>
 <RMSE>  0.972601831     </RMSE>
 <CORR>   1.40129846E-45 </CORR>
 </EXP>
 </STATION>
 <STATION>
 <MEAN_OBS>   2.77726245     </MEAN_OBS>
 <STDV_OBS>  0.898332000     </STDV_OBS>
 <EXP>
 <ID>        2236 </ID>
 <NAME>REF</NAME>
 <NUM>        3167 </NUM>
 <MEAN>   2.68731165     </MEAN>
 <STDV>   5.65694713E-11 </STDV>
 <BIAS>  0.303201288     </BIAS>
 <RMSE>  0.951945126     </RMSE>
 <CORR>   5.65998359E-11 </CORR>
 </EXP>
 <EXP>
 <ID>        2236 </ID>
 <NAME>SCATT</NAME>
 <NUM>        3167 </NUM>
 <MEAN>   0.00000000     </MEAN>
 <STDV>   1.40129846E-45 </STDV>
 <BIAS>  0.304570735     </BIAS>
 <RMSE>  0.951384366     </RMSE>
 <CORR>   1.40129846E-45 </CORR>
 </EXP>
 </STATION>
 <STATION>
 <MEAN_OBS>   2.37916589     </MEAN_OBS>
 <STDV_OBS>  0.885168314     </STDV_OBS>
 <EXP>
 <ID>        2245 </ID>
 <NAME>REF</NAME>
 <NUM>        3176 </NUM>
 <MEAN>   2.58305144     </MEAN>
 <STDV>   5.65998359E-11 </STDV>
 <BIAS>  0.418582290     </BIAS>
 <RMSE>  0.939228714     </RMSE>
 <CORR>   5.65683611E-11 </CORR>
 </EXP>
 <EXP>
 <ID>        2245 </ID>
 <NAME>SCATT</NAME>
 <NUM>        3176 </NUM>
 <MEAN>   1.40129846E-45 </MEAN>
 <STDV>   1.40129846E-45 </STDV>
 <BIAS>  0.416547596     </BIAS>
 <RMSE>  0.940326035     </RMSE>
 <CORR>   1.40129846E-45 </CORR>
 </EXP>
 </STATION>
 <STATION>
 <MEAN_OBS>   2.31639695     </MEAN_OBS>
 <STDV_OBS>  0.886024594     </STDV_OBS>
 <EXP>
 <ID>        2254 </ID>
 <NAME>REF</NAME>
 <NUM>        3169 </NUM>
 <MEAN>   2.61557531     </MEAN>
 <STDV>   5.66107716E-11 </STDV>
 <BIAS>  0.439350605     </BIAS>
 <RMSE>  0.933543861     </RMSE>
 <CORR> -0.317637920     </CORR>
 </EXP>
 <EXP>
 <ID>        2254 </ID>
 <NAME>SCATT</NAME>
 <NUM>        3169 </NUM>
 <MEAN>   1.40129846E-45 </MEAN>
 <STDV>   1.40129846E-45 </STDV>
 <BIAS>  0.438224643     </BIAS>
 <RMSE>  0.933727860     </RMSE>
 <CORR>   1.40129846E-45 </CORR>
 </EXP>
 </STATION>
 <STATION>
 <MEAN_OBS>   2.75791335     </MEAN_OBS>
 <STDV_OBS>  0.827497840     </STDV_OBS>
 <EXP>
 <ID>        2260 </ID>
 <NAME>REF</NAME>
 <NUM>        3185 </NUM>
 <MEAN>   2.85871649     </MEAN>
 <STDV>   5.65693603E-11 </STDV>
 <BIAS>  0.401985139     </BIAS>
 <RMSE>  0.919548929     </RMSE>
 <CORR>   5.65999470E-11 </CORR>
 </EXP>
 <EXP>
 <ID>        2260 </ID>
 <NAME>SCATT</NAME>
 <NUM>        3185 </NUM>
 <MEAN>   1.40129846E-45 </MEAN>
 <STDV>   1.40129846E-45 </STDV>
 <BIAS>  0.401858598     </BIAS>
 <RMSE>  0.919708848     </RMSE>
 <CORR>   1.40129846E-45 </CORR>
 </EXP>
 </STATION>
 <STATION>
 <MEAN_OBS>   2.32150841     </MEAN_OBS>
 <STDV_OBS>  0.913071811     </STDV_OBS>
 <EXP>
 <ID>        2261 </ID>
 <NAME>REF</NAME>
 <NUM>        3181 </NUM>
 <MEAN>   2.63995385     </MEAN>
 <STDV> -0.317637920     </STDV>
 <BIAS>  0.424312502     </BIAS>
 <RMSE>  0.954001069     </RMSE>
 <CORR>   5.65683611E-11 </CORR>
 </EXP>
 <EXP>
 <ID>        2261 </ID>
 <NAME>SCATT</NAME>
 <NUM>        3181 </NUM>
 <MEAN>   1.40129846E-45 </MEAN>
 <STDV>   1.40129846E-45 </STDV>
 <BIAS>  0.425367564     </BIAS>
 <RMSE>  0.953256071     </RMSE>
 <CORR>   1.40129846E-45 </CORR>
 </EXP>
 </STATION>
 <STATION>
 <MEAN_OBS>   2.54641938     </MEAN_OBS>
 <STDV_OBS>  0.852283478     </STDV_OBS>
 <EXP>
 <ID>        2265 </ID>
 <NAME>REF</NAME>
 <NUM>        3157 </NUM>
 <MEAN>   2.70118499     </MEAN>
 <STDV>   5.65694713E-11 </STDV>
 <BIAS>  0.449856848     </BIAS>
 <RMSE>  0.929799557     </RMSE>
 <CORR>   5.66106606E-11 </CORR>
 </EXP>
 <EXP>
 <ID>        2265 </ID>
 <NAME>SCATT</NAME>
 <NUM>        3157 </NUM>
 <MEAN>   0.00000000     </MEAN>
 <STDV>   1.40129846E-45 </STDV>
 <BIAS>  0.449887156     </BIAS>
 <RMSE>  0.929878175     </RMSE>
 <CORR>   1.40129846E-45 </CORR>
 </EXP>
 </STATION>
 <STATION>
 <MEAN_OBS>   2.89637065     </MEAN_OBS>
 <STDV_OBS>   1.00070894     </STDV_OBS>
 <EXP>
 <ID>        2219 </ID>
 <NAME>REF</NAME>
 <NUM>        3181 </NUM>
 <MEAN>   2.85907030     </MEAN>
 <STDV>  -6.42552866E-20 </STDV>
 <BIAS>  0.264214307     </BIAS>
 <RMSE>  0.967548728     </RMSE>
 <CORR>   5.65683611E-11 </CORR>
 </EXP>
 <EXP>
 <ID>        2219 </ID>
 <NAME>SCATT</NAME>
 <NUM>        3181 </NUM>
 <MEAN>   1.40129846E-45 </MEAN>
 <STDV>   0.00000000     </STDV>
 <BIAS>  0.256706774     </BIAS>
 <RMSE>  0.969406366     </RMSE>
 <CORR>   1.40129846E-45 </CORR>
 </EXP>
 </STATION>
 <STATION>
 <MEAN_OBS>   2.09744740     </MEAN_OBS>
 <STDV_OBS>  0.835150242     </STDV_OBS>
 <EXP>
 <ID>        2243 </ID>
 <NAME>REF</NAME>
 <NUM>        3188 </NUM>
 <MEAN>   2.69422650     </MEAN>
 <STDV>   5.66106606E-11 </STDV>
 <BIAS>  0.363937229     </BIAS>
 <RMSE>  0.926930368     </RMSE>
 <CORR>   5.65684721E-11 </CORR>
 </EXP>
 <EXP>
 <ID>        2243 </ID>
 <NAME>SCATT</NAME>
 <NUM>        3188 </NUM>
 <MEAN>   1.40129846E-45 </MEAN>
 <STDV>   1.40129846E-45 </STDV>
 <BIAS>  0.352130860     </BIAS>
 <RMSE>  0.932071328     </RMSE>
 <CORR>   1.40129846E-45 </CORR>
 </EXP>
 </STATION>
 <STATION>
 <MEAN_OBS>   1.72622716     </MEAN_OBS>
 <STDV_OBS>  0.539876401     </STDV_OBS>
 <EXP>
 <ID>        1062 </ID>
 <NAME>REF</NAME>
 <NUM>        3191 </NUM>
 <MEAN>   1.63546383     </MEAN>
 <STDV>   5.65683611E-11 </STDV>
 <BIAS>  0.285004586     </BIAS>
 <RMSE>  0.859699011     </RMSE>
 <CORR>   5.65998359E-11 </CORR>
 </EXP>
 <EXP>
 <ID>        1062 </ID>
 <NAME>SCATT</NAME>
 <NUM>        3191 </NUM>
 <MEAN>   1.40129846E-45 </MEAN>
 <STDV>   1.40129846E-45 </STDV>
 <BIAS>  0.275287330     </BIAS>
 <RMSE>  0.871284246     </RMSE>
 <CORR>   1.40129846E-45 </CORR>
 </EXP>
 </STATION>
 <STATION>
 <MEAN_OBS>   2.87943935     </MEAN_OBS>
 <STDV_OBS>   1.12403202     </STDV_OBS>
 <EXP>
 <ID>        1044 </ID>
 <NAME>REF</NAME>
 <NUM>        3194 </NUM>
 <MEAN>   2.80932570     </MEAN>
 <STDV>   5.65684721E-11 </STDV>
 <BIAS>  0.418147057     </BIAS>
 <RMSE>  0.928550661     </RMSE>
 <CORR>   5.66107716E-11 </CORR>
 </EXP>
 <EXP>
 <ID>        1044 </ID>
 <NAME>SCATT</NAME>
 <NUM>        3194 </NUM>
 <MEAN>   0.00000000     </MEAN>
 <STDV>   1.40129846E-45 </STDV>
 <BIAS>  0.407870859     </BIAS>
 <RMSE>  0.931822658     </RMSE>
 <CORR>   1.40129846E-45 </CORR>
 </EXP>
 </STATION>
 <STATION>
 <MEAN_OBS>   2.21010995     </MEAN_OBS>
 <STDV_OBS>   1.11521125     </STDV_OBS>
 <EXP>
 <ID>        1086 </ID>
 <NAME>REF</NAME>
 <NUM>        2465 </NUM>
 <MEAN>   2.16516185     </MEAN>
 <STDV>  -6.42552866E-20 </STDV>
 <BIAS>  0.347984493     </BIAS>
 <RMSE>  0.950194180     </RMSE>
 <CORR>   5.65694713E-11 </CORR>
 </EXP>
 <EXP>
 <ID>        1086 </ID>
 <NAME>SCATT</NAME>
 <NUM>        2465 </NUM>
 <MEAN>   1.40129846E-45 </MEAN>
 <STDV>   0.00000000     </STDV>
 <BIAS>  0.342471719     </BIAS>
 <RMSE>  0.952520013     </RMSE>
 <CORR>   1.40129846E-45 </CORR>
 </EXP>
 </STATION>
 <STATION>
 <MEAN_OBS>   3.43146729     </MEAN_OBS>
 <STDV_OBS>   1.27683234     </STDV_OBS>
 <EXP>
 <ID>        1161 </ID>
 <NAME>REF</NAME>
 <NUM>        3194 </NUM>
 <MEAN>   3.46035552     </MEAN>
 <STDV>   5.66106606E-11 </STDV>
 <BIAS>  0.339309484     </BIAS>
 <RMSE>  0.964250922     </RMSE>
 <CORR>   5.65998359E-11 </CORR>
 </EXP>
 <EXP>
 <ID>        1161 </ID>
 <NAME>SCATT</NAME>
 <NUM>        3194 </NUM>
 <MEAN>   1.40129846E-45 </MEAN>
 <STDV>   1.40129846E-45 </STDV>
 <BIAS>  0.346185565     </BIAS>
 <RMSE>  0.962758303     </RMSE>
 <CORR>   1.40129846E-45 </CORR>
 </EXP>
 </STATION>
 <STATION>
 <MEAN_OBS>   2.67172170     </MEAN_OBS>
 <STDV_OBS>   1.06233370     </STDV_OBS>
 <EXP>
 <ID>        1001 </ID>
 <NAME>REF</NAME>
 <NUM>        3194 </NUM>
 <MEAN>   2.67434120     </MEAN>
 <STDV>   5.65683611E-11 </STDV>
 <BIAS>  0.273524612     </BIAS>
 <RMSE>  0.967024982     </RMSE>
 <CORR>   5.66107716E-11 </CORR>
 </EXP>
 <EXP>
 <ID>        1001 </ID>
 <NAME>SCATT</NAME>
 <NUM>        3194 </NUM>
 <MEAN>   1.40129846E-45 </MEAN>
 <STDV>   1.40129846E-45 </STDV>
 <BIAS>  0.272280216     </BIAS>
 <RMSE>  0.967319608     </RMSE>
 <CORR>   1.40129846E-45 </CORR>
 </EXP>
 </STATION>
 <STATION>
 <MEAN_OBS>   2.35707331     </MEAN_OBS>
 <STDV_OBS>   1.16526103     </STDV_OBS>
 <EXP>
 <ID>        1023 </ID>
 <NAME>REF</NAME>
 <NUM>        2888 </NUM>
 <MEAN>   2.61627674     </MEAN>
 <STDV>   5.65693603E-11 </STDV>
 <BIAS>  0.406465441     </BIAS>
 <RMSE>  0.956388652     </RMSE>
 <CORR>   5.65694713E-11 </CORR>
 </EXP>
 <EXP>
 <ID>        1023 </ID>
 <NAME>SCATT</NAME>
 <NUM>        2888 </NUM>
 <MEAN>   1.40129846E-45 </MEAN>
 <STDV>   1.40129846E-45 </STDV>
 <BIAS>  0.399535716     </BIAS>
 <RMSE>  0.958113194     </RMSE>
 <CORR>   1.40129846E-45 </CORR>
 </EXP>
 </STATION>
 <STATION>
 <MEAN_OBS>   3.20557141     </MEAN_OBS>
 <STDV_OBS>   1.17540014     </STDV_OBS>
 <EXP>
 <ID>        1033 </ID>
 <NAME>REF</NAME>
 <NUM>        3194 </NUM>
 <MEAN>   3.10010409     </MEAN>
 <STDV> -0.317637920     </STDV>
 <BIAS>  0.383308470     </BIAS>
 <RMSE>  0.948612511     </RMSE>
 <CORR>   5.65998359E-11 </CORR>
 </EXP>
 <EXP>
 <ID>        1033 </ID>
 <NAME>SCATT</NAME>
 <NUM>        3194 </NUM>
 <MEAN>   1.40129846E-45 </MEAN>
 <STDV>   1.40129846E-45 </STDV>
 <BIAS>  0.383566737     </BIAS>
 <RMSE>  0.949941397     </RMSE>
 <CORR>   1.40129846E-45 </CORR>
 </EXP>
 </STATION>
 <STATION>
 <MEAN_OBS>   3.08205128     </MEAN_OBS>
 <STDV_OBS>   1.22481084     </STDV_OBS>
 <EXP>
 <ID>        1180 </ID>
 <NAME>REF</NAME>
 <NUM>        3194 </NUM>
 <MEAN>   3.10351419     </MEAN>
 <STDV>   5.65999470E-11 </STDV>
 <BIAS>  0.329045117     </BIAS>
 <RMSE>  0.965989053     </RMSE>
 <CORR>   5.66107716E-11 </CORR>
 </EXP>
 <EXP>
 <ID>        1180 </ID>
 <NAME>SCATT</NAME>
 <NUM>        3194 </NUM>
 <MEAN>   1.40129846E-45 </MEAN>
 <STDV>   1.40129846E-45 </STDV>
 <BIAS>  0.332624286     </BIAS>
 <RMSE>  0.964920461     </RMSE>
 <CORR>   1.40129846E-45 </CORR>
 </EXP>
 </STATION>
 <STATION>
 <MEAN_OBS>   2.92055893     </MEAN_OBS>
 <STDV_OBS>   1.17973650     </STDV_OBS>
 <EXP>
 <ID>        1025 </ID>
 <NAME>REF</NAME>
 <NUM>        3194 </NUM>
 <MEAN>   2.95687318     </MEAN>
 <STDV>   5.65684721E-11 </STDV>
 <BIAS>  0.321006745     </BIAS>
 <RMSE>  0.966358125     </RMSE>
 <CORR>   5.65694713E-11 </CORR>
 </EXP>
 <EXP>
 <ID>        1025 </ID>
 <NAME>SCATT</NAME>
 <NUM>        3194 </NUM>
 <MEAN>   0.00000000     </MEAN>
 <STDV>   1.40129846E-45 </STDV>
 <BIAS>  0.314002573     </BIAS>
 <RMSE>  0.968491971     </RMSE>
 <CORR>   1.40129846E-45 </CORR>
 </EXP>
 </STATION>
 <STATION>
 <MEAN_OBS>   2.92814302     </MEAN_OBS>
 <STDV_OBS>   1.12122822     </STDV_OBS>
 <EXP>
 <ID>        1132 </ID>
 <NAME>REF</NAME>
 <NUM>        3194 </NUM>
 <MEAN>   2.92192554     </MEAN>
 <STDV>  -6.42552866E-20 </STDV>
 <BIAS>  0.280867785     </BIAS>
 <RMSE>  0.970013261     </RMSE>
 <CORR>   5.65998359E-11 </CORR>
 </EXP>
 <EXP>
 <ID>        1132 </ID>
 <NAME>SCATT</NAME>
 <NUM>        3194 </NUM>
 <MEAN>   1.40129846E-45 </MEAN>
 <STDV>   0.00000000     </STDV>
 <BIAS>  0.284820408     </BIAS>
 <RMSE>  0.969163358     </RMSE>
 <CORR>   1.40129846E-45 </CORR>
 </EXP>
 </STATION>
 <STATION>
 <MEAN_OBS>   3.20772314     </MEAN_OBS>
 <STDV_OBS>   1.24664021     </STDV_OBS>
 <EXP>
 <ID>        1135 </ID>
 <NAME>REF</NAME>
 <NUM>        3194 </NUM>
 <MEAN>   3.16596675     </MEAN>
 <STDV>   5.66106606E-11 </STDV>
 <BIAS>  0.324645489     </BIAS>
 <RMSE>  0.966975927     </RMSE>
 <CORR>   5.66107716E-11 </CORR>
 </EXP>
 <EXP>
 <ID>        1135 </ID>
 <NAME>SCATT</NAME>
 <NUM>        3194 </NUM>
 <MEAN>   1.40129846E-45 </MEAN>
 <STDV>   1.40129846E-45 </STDV>
 <BIAS>  0.318063408     </BIAS>
 <RMSE>  0.968146324     </RMSE>
 <CORR>   1.40129846E-45 </CORR>
 </EXP>
 </STATION>
 <STATION>
 <MEAN_OBS>   2.33326030     </MEAN_OBS>
 <STDV_OBS>   1.02677500     </STDV_OBS>
 <EXP>
 <ID>        1028 </ID>
 <NAME>REF</NAME>
 <NUM>        3187 </NUM>
 <MEAN>   2.32823038     </MEAN>
 <STDV>   5.65693603E-11 </STDV>
 <BIAS>  0.279759735     </BIAS>
 <RMSE>  0.962713957     </RMSE>
 <CORR>   5.65998359E-11 </CORR>
 </EXP>
 <EXP>
 <ID>        1028 </ID>
 <NAME>SCATT</NAME>
 <NUM>        3187 </NUM>
 <MEAN>   1.40129846E-45 </MEAN>
 <STDV>   1.40129846E-45 </STDV>
 <BIAS>  0.265831977     </BIAS>
 <RMSE>  0.966594338     </RMSE>
 <CORR>   1.40129846E-45 </CORR>
 </EXP>
 </STATION>
 <STATION>
 <MEAN_OBS>   2.89023352     </MEAN_OBS>
 <STDV_OBS>   1.08737755     </STDV_OBS>
 <EXP>
 <ID>        2862 </ID>
 <NAME>REF</NAME>
 <NUM>        3194 </NUM>
 <MEAN>   2.82516217     </MEAN>
 <STDV>   5.65999470E-11 </STDV>
 <BIAS>  0.256957591     </BIAS>
 <RMSE>  0.975253701     </RMSE>
 <CORR>   5.65694713E-11 </CORR>
 </EXP>
 <EXP>
 <ID>        2862 </ID>
 <NAME>SCATT</NAME>
 <NUM>        3194 </NUM>
 <MEAN>   1.40129846E-45 </MEAN>
 <STDV>   1.40129846E-45 </STDV>
 <BIAS>  0.257667989     </BIAS>
 <RMSE>  0.975122333     </RMSE>
 <CORR>   1.40129846E-45 </CORR>
 </EXP>
 </STATION>
 <STATION>
 <MEAN_OBS>   1.90763259     </MEAN_OBS>
 <STDV_OBS>   1.10505974     </STDV_OBS>
 <EXP>
 <ID>        2807 </ID>
 <NAME>REF</NAME>
 <NUM>        3194 </NUM>
 <MEAN>   1.96398985     </MEAN>
 <STDV>   5.65684721E-11 </STDV>
 <BIAS>  0.293711275     </BIAS>
 <RMSE>  0.964189291     </RMSE>
 <CORR>   5.65998359E-11 </CORR>
 </EXP>
 <EXP>
 <ID>        2807 </ID>
 <NAME>SCATT</NAME>
 <NUM>        3194 </NUM>
 <MEAN>   0.00000000     </MEAN>
 <STDV>   1.40129846E-45 </STDV>
 <BIAS>  0.289128423     </BIAS>
 <RMSE>  0.965470850     </RMSE>
 <CORR>   1.40129846E-45 </CORR>
 </EXP>
 </STATION>
 <STATION>
 <MEAN_OBS>   2.64002085     </MEAN_OBS>
 <STDV_OBS>   1.07243979     </STDV_OBS>
 <EXP>
 <ID>        2880 </ID>
 <NAME>REF</NAME>
 <NUM>        3194 </NUM>
 <MEAN>   2.73957610     </MEAN>
 <STDV>  -6.42552866E-20 </STDV>
 <BIAS>  0.243462995     </BIAS>
 <RMSE>  0.979120195     </RMSE>
 <CORR>   5.66107716E-11 </CORR>
 </EXP>
 <EXP>
 <ID>        2880 </ID>
 <NAME>SCATT</NAME>
 <NUM>        3194 </NUM>
 <MEAN>   1.40129846E-45 </MEAN>
 <STDV>   0.00000000     </STDV>
 <BIAS>  0.248516962     </BIAS>
 <RMSE>  0.978349924     </RMSE>
 <CORR>   1.40129846E-45 </CORR>
 </EXP>
 </STATION>
 <STATION>
 <MEAN_OBS>   2.14580393     </MEAN_OBS>
 <STDV_OBS>   1.09055805     </STDV_OBS>
 <EXP>
 <ID>        2844 </ID>
 <NAME>REF</NAME>
 <NUM>        3194 </NUM>
 <MEAN>   2.32951355     </MEAN>
 <STDV>   5.66106606E-11 </STDV>
 <BIAS>  0.352503538     </BIAS>
 <RMSE>  0.950205863     </RMSE>
 <CORR>   5.65694713E-11 </CORR>
 </EXP>
 <EXP>
 <ID>        2844 </ID>
 <NAME>SCATT</NAME>
 <NUM>        3194 </NUM>
 <MEAN>   1.40129846E-45 </MEAN>
 <STDV>   1.40129846E-45 </STDV>
 <BIAS>  0.354056656     </BIAS>
 <RMSE>  0.949790895     </RMSE>
 <CORR>   1.40129846E-45 </CORR>
 </EXP>
 </STATION>
 <STATION>
 <MEAN_OBS>   2.00801587     </MEAN_OBS>
 <STDV_OBS>   1.17428279     </STDV_OBS>
 <EXP>
 <ID>        2836 </ID>
 <NAME>REF</NAME>
 <NUM>        3194 </NUM>
 <MEAN>   2.01198578     </MEAN>
 <STDV>   5.65693603E-11 </STDV>
 <BIAS>  0.363921344     </BIAS>
 <RMSE>  0.950280249     </RMSE>
 <CORR>   5.66107716E-11 </CORR>
 </EXP>
 <EXP>
 <ID>        2836 </ID>
 <NAME>SCATT</NAME>
 <NUM>        3194 </NUM>
 <MEAN>   1.40129846E-45 </MEAN>
 <STDV>   1.40129846E-45 </STDV>
 <BIAS>  0.359359026     </BIAS>
 <RMSE>  0.952251971     </RMSE>
 <CORR>   1.40129846E-45 </CORR>
 </EXP>
 </STATION>
 <STATION>
 <MEAN_OBS>   2.16509843     </MEAN_OBS>
 <STDV_OBS>   1.09146702     </STDV_OBS>
 <EXP>
 <ID>        2814 </ID>
 <NAME>REF</NAME>
 <NUM>        3194 </NUM>
 <MEAN>   2.29712319     </MEAN>
 <STDV> -0.317637920     </STDV>
 <BIAS>  0.343409896     </BIAS>
 <RMSE>  0.956941307     </RMSE>
 <CORR>   5.65694713E-11 </CORR>
 </EXP>
 <EXP>
 <ID>        2814 </ID>
 <NAME>SCATT</NAME>
 <NUM>        3194 </NUM>
 <MEAN>   1.40129846E-45 </MEAN>
 <STDV>   1.40129846E-45 </STDV>
 <BIAS>  0.330642462     </BIAS>
 <RMSE>  0.960187495     </RMSE>
 <CORR>   1.40129846E-45 </CORR>
 </EXP>
 </STATION>
 <STATION>
 <MEAN_OBS>   2.12540269     </MEAN_OBS>
 <STDV_OBS>   1.13138628     </STDV_OBS>
 <EXP>
 <ID>        2849 </ID>
 <NAME>REF</NAME>
 <NUM>        3194 </NUM>
 <MEAN>   2.23589301     </MEAN>
 <STDV>   5.65999470E-11 </STDV>
 <BIAS>  0.340340197     </BIAS>
 <RMSE>  0.962662637     </RMSE>
 <CORR>   5.65998359E-11 </CORR>
 </EXP>
 <EXP>
 <ID>        2849 </ID>
 <NAME>SCATT</NAME>
 <NUM>        3194 </NUM>
 <MEAN>   1.40129846E-45 </MEAN>
 <STDV>   1.40129846E-45 </STDV>
 <BIAS>  0.329800487     </BIAS>
 <RMSE>  0.965109468     </RMSE>
 <CORR>   1.40129846E-45 </CORR>
 </EXP>
 </STATION>
 <STATION>
 <MEAN_OBS>   1.79906702     </MEAN_OBS>
 <STDV_OBS>   1.08307242     </STDV_OBS>
 <EXP>
 <ID>        2801 </ID>
 <NAME>REF</NAME>
 <NUM>        3194 </NUM>
 <MEAN>   2.04392886     </MEAN>
 <STDV>   5.65684721E-11 </STDV>
 <BIAS>  0.414666742     </BIAS>
 <RMSE>  0.927511930     </RMSE>
 <CORR>   5.66107716E-11 </CORR>
 </EXP>
 <EXP>
 <ID>        2801 </ID>
 <NAME>SCATT</NAME>
 <NUM>        3194 </NUM>
 <MEAN>   0.00000000     </MEAN>
 <STDV>   1.40129846E-45 </STDV>
 <BIAS>  0.396968693     </BIAS>
 <RMSE>  0.933725476     </RMSE>
 <CORR>   1.40129846E-45 </CORR>
 </EXP>
 </STATION>
 <STATION>
 <MEAN_OBS>   1.61424255     </MEAN_OBS>
 <STDV_OBS>   1.13789272     </STDV_OBS>
 <EXP>
 <ID>        2805 </ID>
 <NAME>REF</NAME>
 <NUM>        3194 </NUM>
 <MEAN>   1.69043696     </MEAN>
 <STDV>  -6.42552866E-20 </STDV>
 <BIAS>  0.475007653     </BIAS>
 <RMSE>  0.917945802     </RMSE>
 <CORR>   5.65694713E-11 </CORR>
 </EXP>
 <EXP>
 <ID>        2805 </ID>
 <NAME>SCATT</NAME>
 <NUM>        3194 </NUM>
 <MEAN>   1.40129846E-45 </MEAN>
 <STDV>   0.00000000     </STDV>
 <BIAS>  0.461181313     </BIAS>
 <RMSE>  0.922546208     </RMSE>
 <CORR>   1.40129846E-45 </CORR>
 </EXP>
 </STATION>
 <STATION>
 <MEAN_OBS>   1.89378631     </MEAN_OBS>
 <STDV_OBS>   1.06548381     </STDV_OBS>
 <EXP>
 <ID>        2835 </ID>
 <NAME>REF</NAME>
 <NUM>        3194 </NUM>
 <MEAN>   2.09001327     </MEAN>
 <STDV>   5.66106606E-11 </STDV>
 <BIAS>  0.446842551     </BIAS>
 <RMSE>  0.918984056     </RMSE>
 <CORR>   5.65998359E-11 </CORR>
 </EXP>
 <EXP>
 <ID>        2835 </ID>
 <NAME>SCATT</NAME>
 <NUM>        3194 </NUM>
 <MEAN>   1.40129846E-45 </MEAN>
 <STDV>   1.40129846E-45 </STDV>
 <BIAS>  0.436631799     </BIAS>
 <RMSE>  0.922849178     </RMSE>
 <CORR>   1.40129846E-45 </CORR>
 </EXP>
 </STATION>
 <STATION>
 <MEAN_OBS>   1.06188273     </MEAN_OBS>
 <STDV_OBS>  0.456154764     </STDV_OBS>
 <EXP>
 <ID>        1008 </ID>
 <NAME>REF</NAME>
 <NUM>        2606 </NUM>
 <MEAN>   1.06631982     </MEAN>
 <STDV>   5.65683611E-11 </STDV>
 <BIAS>  0.180815190     </BIAS>
 <RMSE>  0.921503067     </RMSE>
 <CORR>   5.66107716E-11 </CORR>
 </EXP>
 <EXP>
 <ID>        1008 </ID>
 <NAME>SCATT</NAME>
 <NUM>        2606 </NUM>
 <MEAN>   1.40129846E-45 </MEAN>
 <STDV>   1.40129846E-45 </STDV>
 <BIAS>  0.180305719     </BIAS>
 <RMSE>  0.921204150     </RMSE>
 <CORR>   1.40129846E-45 </CORR>
 </EXP>
 </STATION>
 <STATION>
 <MEAN_OBS>   2.99828625     </MEAN_OBS>
 <STDV_OBS>   1.19360697     </STDV_OBS>
 <EXP>
 <ID>        1026 </ID>
 <NAME>REF</NAME>
 <NUM>        3194 </NUM>
 <MEAN>   2.91909361     </MEAN>
 <STDV>   5.65693603E-11 </STDV>
 <BIAS>  0.338962466     </BIAS>
 <RMSE>  0.962750256     </RMSE>
 <CORR>   5.65694713E-11 </CORR>
 </EXP>
 <EXP>
 <ID>        1026 </ID>
 <NAME>SCATT</NAME>
 <NUM>        3194 </NUM>
 <MEAN>   1.40129846E-45 </MEAN>
 <STDV>   1.40129846E-45 </STDV>
 <BIAS>  0.328893989     </BIAS>
 <RMSE>  0.965473950     </RMSE>
 <CORR>   1.40129846E-45 </CORR>
 </EXP>
 </STATION>
 <STATION>
 <MEAN_OBS>   3.71840739     </MEAN_OBS>
 <STDV_OBS>   1.29158115     </STDV_OBS>
 <EXP>
 <ID>        1160 </ID>
 <NAME>REF</NAME>
 <NUM>        3194 </NUM>
 <MEAN>   3.52661705     </MEAN>
 <STDV> -0.317637920     </STDV>
 <BIAS>  0.352425307     </BIAS>
 <RMSE>  0.962404191     </RMSE>
 <CORR>   5.65998359E-11 </CORR>
 </EXP>
 <EXP>
 <ID>        1160 </ID>
 <NAME>SCATT</NAME>
 <NUM>        3194 </NUM>
 <MEAN>   1.40129846E-45 </MEAN>
 <STDV>   1.40129846E-45 </STDV>
 <BIAS>  0.353086084     </BIAS>
 <RMSE>  0.962260187     </RMSE>
 <CORR>   1.40129846E-45 </CORR>
 </EXP>
 </STATION>
 <STATION>
 <MEAN_OBS>   1.30362213     </MEAN_OBS>
 <STDV_OBS>  0.281121939     </STDV_OBS>
 <EXP>
 <ID>        1002 </ID>
 <NAME>REF</NAME>
 <NUM>        2892 </NUM>
 <MEAN>   1.24453509     </MEAN>
 <STDV>   5.65999470E-11 </STDV>
 <BIAS>  0.172218889     </BIAS>
 <RMSE>  0.814198196     </RMSE>
 <CORR>   5.66107716E-11 </CORR>
 </EXP>
 <EXP>
 <ID>        1002 </ID>
 <NAME>SCATT</NAME>
 <NUM>        2892 </NUM>
 <MEAN>   1.40129846E-45 </MEAN>
 <STDV>   1.40129846E-45 </STDV>
 <BIAS>  0.168408021     </BIAS>
 <RMSE>  0.822009742     </RMSE>
 <CORR>   1.40129846E-45 </CORR>
 </EXP>
 </STATION>
 <STATION>
 <MEAN_OBS>   1.19405842     </MEAN_OBS>
 <STDV_OBS>  0.414218843     </STDV_OBS>
 <EXP>
 <ID>        1006 </ID>
 <NAME>REF</NAME>
 <NUM>        2993 </NUM>
 <MEAN>   1.13566875     </MEAN>
 <STDV>   5.65684721E-11 </STDV>
 <BIAS>  0.209426895     </BIAS>
 <RMSE>  0.868805408     </RMSE>
 <CORR>   5.65694713E-11 </CORR>
 </EXP>
 <EXP>
 <ID>        1006 </ID>
 <NAME>SCATT</NAME>
 <NUM>        2993 </NUM>
 <MEAN>   0.00000000     </MEAN>
 <STDV>   1.40129846E-45 </STDV>
 <BIAS>  0.208077565     </BIAS>
 <RMSE>  0.869883358     </RMSE>
 <CORR>   1.40129846E-45 </CORR>
 </EXP>
 </STATION>
 <STATION>
 <MEAN_OBS>  0.887320340     </MEAN_OBS>
 <STDV_OBS>  0.285140693     </STDV_OBS>
 <EXP>
 <ID>        1011 </ID>
 <NAME>REF</NAME>
 <NUM>        2959 </NUM>
 <MEAN>  0.866452694     </MEAN>
 <STDV>  -6.42552866E-20 </STDV>
 <BIAS>  0.163760468     </BIAS>
 <RMSE>  0.835051835     </RMSE>
 <CORR>   5.65998359E-11 </CORR>
 </EXP>
 <EXP>
 <ID>        1011 </ID>
 <NAME>SCATT</NAME>
 <NUM>        2959 </NUM>
 <MEAN>   1.40129846E-45 </MEAN>
 <STDV>   0.00000000     </STDV>
 <BIAS>  0.157891050     </BIAS>
 <RMSE>  0.844051600     </RMSE>
 <CORR>   1.40129846E-45 </CORR>
 </EXP>
 </STATION>
 <STATION>
 <MEAN_OBS>   3.01002216     </MEAN_OBS>
 <STDV_OBS>   1.22453225     </STDV_OBS>
 <EXP>
 <ID>        1158 </ID>
 <NAME>REF</NAME>
 <NUM>        3194 </NUM>
 <MEAN>   3.00055814     </MEAN>
 <STDV>   5.66106606E-11 </STDV>
 <BIAS>  0.328896940     </BIAS>
 <RMSE>  0.963057339     </RMSE>
 <CORR>  -6.42552866E-20 </CORR>
 </EXP>
 <EXP>
 <ID>        1158 </ID>
 <NAME>SCATT</NAME>
 <NUM>        3194 </NUM>
 <MEAN>   1.40129846E-45 </MEAN>
 <STDV>   1.40129846E-45 </STDV>
 <BIAS>  0.322128654     </BIAS>
 <RMSE>  0.964777231     </RMSE>
 <CORR>   0.00000000     </CORR>
 </EXP>
 </STATION>
 <STATION>
 <MEAN_OBS>   2.15006185     </MEAN_OBS>
 <STDV_OBS>   1.03059971     </STDV_OBS>
 <EXP>
 <ID>        1198 </ID>
 <NAME>REF</NAME>
 <NUM>        3148 </NUM>
 <MEAN>   2.30418539     </MEAN>
 <STDV>   5.65693603E-11 </STDV>
 <BIAS>  0.380680174     </BIAS>
 <RMSE>  0.931175411     </RMSE>
 <CORR>   5.65683611E-11 </CORR>
 </EXP>
 <EXP>
 <ID>        1198 </ID>
 <NAME>SCATT</NAME>
 <NUM>        3148 </NUM>
 <MEAN>   1.40129846E-45 </MEAN>
 <STDV>   1.40129846E-45 </STDV>
 <BIAS>  0.368761837     </BIAS>
 <RMSE>  0.935142934     </RMSE>
 <CORR>   1.40129846E-45 </CORR>
 </EXP>
 </STATION>
 <STATION>
 <MEAN_OBS>   2.77550483     </MEAN_OBS>
 <STDV_OBS>   1.02467644     </STDV_OBS>
 <EXP>
 <ID>        1068 </ID>
 <NAME>REF</NAME>
 <NUM>        3180 </NUM>
 <MEAN>   2.63948250     </MEAN>
 <STDV>  -6.42552866E-20 </STDV>
 <BIAS>  0.329646021     </BIAS>
 <RMSE>  0.947101414     </RMSE>
 <CORR>   5.65998359E-11 </CORR>
 </EXP>
 <EXP>
 <ID>        1068 </ID>
 <NAME>SCATT</NAME>
 <NUM>        3180 </NUM>
 <MEAN>   1.40129846E-45 </MEAN>
 <STDV>   0.00000000     </STDV>
 <BIAS>  0.318122417     </BIAS>
 <RMSE>  0.951223969     </RMSE>
 <CORR>   1.40129846E-45 </CORR>
 </EXP>
 </STATION>
 <STATION>
 <MEAN_OBS>   2.46082902     </MEAN_OBS>
 <STDV_OBS>   1.13030434     </STDV_OBS>
 <EXP>
 <ID>        1074 </ID>
 <NAME>REF</NAME>
 <NUM>        3150 </NUM>
 <MEAN>   2.48466873     </MEAN>
 <STDV>   5.65694713E-11 </STDV>
 <BIAS>  0.324128777     </BIAS>
 <RMSE>  0.957606375     </RMSE>
 <CORR>   5.66107716E-11 </CORR>
 </EXP>
 <EXP>
 <ID>        1074 </ID>
 <NAME>SCATT</NAME>
 <NUM>        3150 </NUM>
 <MEAN>   1.40129846E-45 </MEAN>
 <STDV>   1.40129846E-45 </STDV>
 <BIAS>  0.318131953     </BIAS>
 <RMSE>  0.959600389     </RMSE>
 <CORR>   1.40129846E-45 </CORR>
 </EXP>
 </STATION>
 <STATION>
 <MEAN_OBS>   2.49383759     </MEAN_OBS>
 <STDV_OBS>   1.11326051     </STDV_OBS>
 <EXP>
 <ID>        1083 </ID>
 <NAME>REF</NAME>
 <NUM>        3180 </NUM>
 <MEAN>   2.45736527     </MEAN>
 <STDV>   5.65999470E-11 </STDV>
 <BIAS>  0.358941555     </BIAS>
 <RMSE>  0.946436703     </RMSE>
 <CORR>   5.65683611E-11 </CORR>
 </EXP>
 <EXP>
 <ID>        1083 </ID>
 <NAME>SCATT</NAME>
 <NUM>        3180 </NUM>
 <MEAN>   1.40129846E-45 </MEAN>
 <STDV>   1.40129846E-45 </STDV>
 <BIAS>  0.346645534     </BIAS>
 <RMSE>  0.950327098     </RMSE>
 <CORR>   1.40129846E-45 </CORR>
 </EXP>
 </STATION>
 <STATION>
 <MEAN_OBS>   2.40966511     </MEAN_OBS>
 <STDV_OBS>   1.00902915     </STDV_OBS>
 <EXP>
 <ID>        1088 </ID>
 <NAME>REF</NAME>
 <NUM>        3180 </NUM>
 <MEAN>   2.47067332     </MEAN>
 <STDV>   5.65684721E-11 </STDV>
 <BIAS>  0.315366685     </BIAS>
 <RMSE>  0.949780941     </RMSE>
 <CORR>   5.65998359E-11 </CORR>
 </EXP>
 <EXP>
 <ID>        1088 </ID>
 <NAME>SCATT</NAME>
 <NUM>        3180 </NUM>
 <MEAN>   1.40129846E-45 </MEAN>
 <STDV>   1.40129846E-45 </STDV>
 <BIAS>  0.312152117     </BIAS>
 <RMSE>  0.952106953     </RMSE>
 <CORR>   1.40129846E-45 </CORR>
 </EXP>
 </STATION>
 <STATION>
 <MEAN_OBS>   3.67312384     </MEAN_OBS>
 <STDV_OBS>   1.27744651     </STDV_OBS>
 <EXP>
 <ID>        1139 </ID>
 <NAME>REF</NAME>
 <NUM>        3153 </NUM>
 <MEAN>   3.60228658     </MEAN>
 <STDV> -0.317637920     </STDV>
 <BIAS>  0.394204557     </BIAS>
 <RMSE>  0.953422904     </RMSE>
 <CORR>   5.66107716E-11 </CORR>
 </EXP>
 <EXP>
 <ID>        1139 </ID>
 <NAME>SCATT</NAME>
 <NUM>        3153 </NUM>
 <MEAN>   1.40129846E-45 </MEAN>
 <STDV>   1.40129846E-45 </STDV>
 <BIAS>  0.400793672     </BIAS>
 <RMSE>  0.950623453     </RMSE>
 <CORR>   1.40129846E-45 </CORR>
 </EXP>
 </STATION>
 <STATION>
 <MEAN_OBS>   2.82999778     </MEAN_OBS>
 <STDV_OBS>   1.29706287     </STDV_OBS>
 <EXP>
 <ID>        1151 </ID>
 <NAME>REF</NAME>
 <NUM>        3194 </NUM>
 <MEAN>   2.96089315     </MEAN>
 <STDV>   5.66106606E-11 </STDV>
 <BIAS>  0.475325525     </BIAS>
 <RMSE>  0.932043254     </RMSE>
 <CORR>   5.65683611E-11 </CORR>
 </EXP>
 <EXP>
 <ID>        1151 </ID>
 <NAME>SCATT</NAME>
 <NUM>        3194 </NUM>
 <MEAN>   1.40129846E-45 </MEAN>
 <STDV>   1.40129846E-45 </STDV>
 <BIAS>  0.476037562     </BIAS>
 <RMSE>  0.931990027     </RMSE>
 <CORR>   1.40129846E-45 </CORR>
 </EXP>
 </STATION>
 <STATION>
 <MEAN_OBS>   2.33342934     </MEAN_OBS>
 <STDV_OBS>   1.05599976     </STDV_OBS>
 <EXP>
 <ID>        2847 </ID>
 <NAME>REF</NAME>
 <NUM>        3194 </NUM>
 <MEAN>   2.42931342     </MEAN>
 <STDV>   5.65693603E-11 </STDV>
 <BIAS>  0.256653398     </BIAS>
 <RMSE>  0.973554969     </RMSE>
 <CORR>   5.65998359E-11 </CORR>
 </EXP>
 <EXP>
 <ID>        2847 </ID>
 <NAME>SCATT</NAME>
 <NUM>        3194 </NUM>
 <MEAN>   0.00000000     </MEAN>
 <STDV>   1.40129846E-45 </STDV>
 <BIAS>  0.241292864     </BIAS>
 <RMSE>  0.976700127     </RMSE>
 <CORR>   1.40129846E-45 </CORR>
 </EXP>
 </STATION>
 <STATION>
 <MEAN_OBS>   2.20760655     </MEAN_OBS>
 <STDV_OBS>   1.07533646     </STDV_OBS>
 <EXP>
 <ID>        2813 </ID>
 <NAME>REF</NAME>
 <NUM>        3139 </NUM>
 <MEAN>   2.35465407     </MEAN>
 <STDV>  -6.42552866E-20 </STDV>
 <BIAS>  0.318200618     </BIAS>
 <RMSE>  0.965458214     </RMSE>
 <CORR>   5.66107716E-11 </CORR>
 </EXP>
 <EXP>
 <ID>        2813 </ID>
 <NAME>SCATT</NAME>
 <NUM>        3139 </NUM>
 <MEAN>   1.40129846E-45 </MEAN>
 <STDV>   0.00000000     </STDV>
 <BIAS>  0.303515255     </BIAS>
 <RMSE>  0.968888938     </RMSE>
 <CORR>   1.40129846E-45 </CORR>
 </EXP>
 </STATION>
 <STATION>
 <MEAN_OBS>   2.33277321     </MEAN_OBS>
 <STDV_OBS>   1.08436775     </STDV_OBS>
 <EXP>
 <ID>        2705 </ID>
 <NAME>REF</NAME>
 <NUM>        3194 </NUM>
 <MEAN>   2.20181465     </MEAN>
 <STDV>   5.65999470E-11 </STDV>
 <BIAS>  0.320495993     </BIAS>
 <RMSE>  0.963000119     </RMSE>
 <CORR>   5.65694713E-11 </CORR>
 </EXP>
 <EXP>
 <ID>        2705 </ID>
 <NAME>SCATT</NAME>
 <NUM>        3194 </NUM>
 <MEAN>   1.40129846E-45 </MEAN>
 <STDV>   1.40129846E-45 </STDV>
 <BIAS>  0.316531330     </BIAS>
 <RMSE>  0.965611160     </RMSE>
 <CORR>   1.40129846E-45 </CORR>
 </EXP>
 </STATION>
 <STATION>
 <MEAN_OBS>   2.02564955     </MEAN_OBS>
 <STDV_OBS>   1.25432801     </STDV_OBS>
 <EXP>
 <ID>        2745 </ID>
 <NAME>REF</NAME>
 <NUM>        3194 </NUM>
 <MEAN>   1.96948779     </MEAN>
 <STDV>   5.65684721E-11 </STDV>
 <BIAS>  0.342702568     </BIAS>
 <RMSE>  0.961623430     </RMSE>
 <CORR>   5.66107716E-11 </CORR>
 </EXP>
 <EXP>
 <ID>        2745 </ID>
 <NAME>SCATT</NAME>
 <NUM>        3194 </NUM>
 <MEAN>   1.40129846E-45 </MEAN>
 <STDV>   1.40129846E-45 </STDV>
 <BIAS>  0.331954628     </BIAS>
 <RMSE>  0.964388251     </RMSE>
 <CORR>   1.40129846E-45 </CORR>
 </EXP>
 </STATION>
 <STATION>
 <MEAN_OBS>   2.15884566     </MEAN_OBS>
 <STDV_OBS>  0.977748156     </STDV_OBS>
 <EXP>
 <ID>        2820 </ID>
 <NAME>REF</NAME>
 <NUM>        3180 </NUM>
 <MEAN>   1.97551441     </MEAN>
 <STDV> -0.317637920     </STDV>
 <BIAS>  0.338142157     </BIAS>
 <RMSE>  0.941406846     </RMSE>
 <CORR>   5.65683611E-11 </CORR>
 </EXP>
 <EXP>
 <ID>        2820 </ID>
 <NAME>SCATT</NAME>
 <NUM>        3180 </NUM>
 <MEAN>   1.40129846E-45 </MEAN>
 <STDV>   1.40129846E-45 </STDV>
 <BIAS>  0.347103536     </BIAS>
 <RMSE>  0.939161003     </RMSE>
 <CORR>   1.40129846E-45 </CORR>
 </EXP>
 </STATION>
 <STATION>
 <MEAN_OBS>   2.20595288     </MEAN_OBS>
 <STDV_OBS>   1.02827394     </STDV_OBS>
 <EXP>
 <ID>        2821 </ID>
 <NAME>REF</NAME>
 <NUM>        3194 </NUM>
 <MEAN>   2.01944661     </MEAN>
 <STDV>   5.66106606E-11 </STDV>
 <BIAS>  0.314425915     </BIAS>
 <RMSE>  0.954559565     </RMSE>
 <CORR>   5.65694713E-11 </CORR>
 </EXP>
 <EXP>
 <ID>        2821 </ID>
 <NAME>SCATT</NAME>
 <NUM>        3194 </NUM>
 <MEAN>   1.40129846E-45 </MEAN>
 <STDV>   1.40129846E-45 </STDV>
 <BIAS>  0.317926854     </BIAS>
 <RMSE>  0.954459667     </RMSE>
 <CORR>   1.40129846E-45 </CORR>
 </EXP>
 </STATION>
 <STATION>
 <MEAN_OBS>   2.14851451     </MEAN_OBS>
 <STDV_OBS>   1.07995558     </STDV_OBS>
 <EXP>
 <ID>        2882 </ID>
 <NAME>REF</NAME>
 <NUM>        3194 </NUM>
 <MEAN>   2.04422235     </MEAN>
 <STDV>   5.65683611E-11 </STDV>
 <BIAS>  0.252260655     </BIAS>
 <RMSE>  0.974807501     </RMSE>
 <CORR>   5.66107716E-11 </CORR>
 </EXP>
 <EXP>
 <ID>        2882 </ID>
 <NAME>SCATT</NAME>
 <NUM>        3194 </NUM>
 <MEAN>   0.00000000     </MEAN>
 <STDV>   1.40129846E-45 </STDV>
 <BIAS>  0.241111428     </BIAS>
 <RMSE>  0.978700161     </RMSE>
 <CORR>   1.40129846E-45 </CORR>
 </EXP>
 </STATION>
 <STATION>
 <MEAN_OBS>   2.09066176     </MEAN_OBS>
 <STDV_OBS>   1.04704905     </STDV_OBS>
 <EXP>
 <ID>        2817 </ID>
 <NAME>REF</NAME>
 <NUM>        3194 </NUM>
 <MEAN>   1.85675526     </MEAN>
 <STDV>   5.65694713E-11 </STDV>
 <BIAS>  0.335998327     </BIAS>
 <RMSE>  0.954361141     </RMSE>
 <CORR>   5.65693603E-11 </CORR>
 </EXP>
 <EXP>
 <ID>        2817 </ID>
 <NAME>SCATT</NAME>
 <NUM>        3194 </NUM>
 <MEAN>   1.40129846E-45 </MEAN>
 <STDV>   1.40129846E-45 </STDV>
 <BIAS>  0.339183003     </BIAS>
 <RMSE>  0.953961015     </RMSE>
 <CORR>   1.40129846E-45 </CORR>
 </EXP>
 </STATION>
 <STATION>
 <MEAN_OBS>   2.03682613     </MEAN_OBS>
 <STDV_OBS>   1.13398588     </STDV_OBS>
 <EXP>
 <ID>        2818 </ID>
 <NAME>REF</NAME>
 <NUM>        3194 </NUM>
 <MEAN>   1.92482781     </MEAN>
 <STDV> -0.317637920     </STDV>
 <BIAS>  0.302075416     </BIAS>
 <RMSE>  0.965193987     </RMSE>
 <CORR>   5.65684721E-11 </CORR>
 </EXP>
 <EXP>
 <ID>        2818 </ID>
 <NAME>SCATT</NAME>
 <NUM>        3194 </NUM>
 <MEAN>   1.40129846E-45 </MEAN>
 <STDV>   1.40129846E-45 </STDV>
 <BIAS>  0.296636254     </BIAS>
 <RMSE>  0.966882825     </RMSE>
 <CORR>   1.40129846E-45 </CORR>
 </EXP>
 </STATION>
 <STATION>
 <MEAN_OBS>   1.65989971     </MEAN_OBS>
 <STDV_OBS>   1.04664433     </STDV_OBS>
 <EXP>
 <ID>        2726 </ID>
 <NAME>REF</NAME>
 <NUM>        3194 </NUM>
 <MEAN>   1.83710074     </MEAN>
 <STDV>   5.66106606E-11 </STDV>
 <BIAS>  0.419841290     </BIAS>
 <RMSE>  0.918472767     </RMSE>
 <CORR>   5.66107716E-11 </CORR>
 </EXP>
 <EXP>
 <ID>        2726 </ID>
 <NAME>SCATT</NAME>
 <NUM>        3194 </NUM>
 <MEAN>   1.40129846E-45 </MEAN>
 <STDV>   1.40129846E-45 </STDV>
 <BIAS>  0.414647758     </BIAS>
 <RMSE>  0.920955598     </RMSE>
 <CORR>   1.40129846E-45 </CORR>
 </EXP>
 </STATION>
 <STATION>
 <MEAN_OBS>   1.84935093     </MEAN_OBS>
 <STDV_OBS>   1.11518288     </STDV_OBS>
 <EXP>
 <ID>        2857 </ID>
 <NAME>REF</NAME>
 <NUM>        3194 </NUM>
 <MEAN>   1.77430022     </MEAN>
 <STDV>   5.65683611E-11 </STDV>
 <BIAS>  0.304549664     </BIAS>
 <RMSE>  0.962302208     </RMSE>
 <CORR>   5.65693603E-11 </CORR>
 </EXP>
 <EXP>
 <ID>        2857 </ID>
 <NAME>SCATT</NAME>
 <NUM>        3194 </NUM>
 <MEAN>   0.00000000     </MEAN>
 <STDV>   1.40129846E-45 </STDV>
 <BIAS>  0.291651309     </BIAS>
 <RMSE>  0.965791583     </RMSE>
 <CORR>   1.40129846E-45 </CORR>
 </EXP>
 </STATION>
 <STATION>
 <MEAN_OBS>   1.86089122     </MEAN_OBS>
 <STDV_OBS>   1.18080664     </STDV_OBS>
 <EXP>
 <ID>        2825 </ID>
 <NAME>REF</NAME>
 <NUM>        3194 </NUM>
 <MEAN>   2.07157779     </MEAN>
 <STDV>  -6.42552866E-20 </STDV>
 <BIAS>  0.456999421     </BIAS>
 <RMSE>  0.931469858     </RMSE>
 <CORR>   5.65684721E-11 </CORR>
 </EXP>
 <EXP>
 <ID>        2825 </ID>
 <NAME>SCATT</NAME>
 <NUM>        3194 </NUM>
 <MEAN>   1.40129846E-45 </MEAN>
 <STDV>   0.00000000     </STDV>
 <BIAS>  0.448759913     </BIAS>
 <RMSE>  0.933994830     </RMSE>
 <CORR>   1.40129846E-45 </CORR>
 </EXP>
 </STATION>
 <STATION>
 <MEAN_OBS>   2.36603737     </MEAN_OBS>
 <STDV_OBS>   1.02373886     </STDV_OBS>
 <EXP>
 <ID>        2888 </ID>
 <NAME>REF</NAME>
 <NUM>        3194 </NUM>
 <MEAN>   2.12909937     </MEAN>
 <STDV>   5.65999470E-11 </STDV>
 <BIAS>  0.308112800     </BIAS>
 <RMSE>  0.966878712     </RMSE>
 <CORR>   5.65693603E-11 </CORR>
 </EXP>
 <EXP>
 <ID>        2888 </ID>
 <NAME>SCATT</NAME>
 <NUM>        3194 </NUM>
 <MEAN>   1.40129846E-45 </MEAN>
 <STDV>   1.40129846E-45 </STDV>
 <BIAS>  0.302014202     </BIAS>
 <RMSE>  0.967794478     </RMSE>
 <CORR>   1.40129846E-45 </CORR>
 </EXP>
 </STATION>
 <STATION>
 <MEAN_OBS>   2.60405159     </MEAN_OBS>
 <STDV_OBS>   1.13304520     </STDV_OBS>
 <EXP>
 <ID>        2864 </ID>
 <NAME>REF</NAME>
 <NUM>        3194 </NUM>
 <MEAN>   2.70638824     </MEAN>
 <STDV> -0.317637920     </STDV>
 <BIAS>  0.297863543     </BIAS>
 <RMSE>  0.971892297     </RMSE>
 <CORR>   5.65694713E-11 </CORR>
 </EXP>
 <EXP>
 <ID>        2864 </ID>
 <NAME>SCATT</NAME>
 <NUM>        3194 </NUM>
 <MEAN>   1.40129846E-45 </MEAN>
 <STDV>   1.40129846E-45 </STDV>
 <BIAS>  0.296614766     </BIAS>
 <RMSE>  0.972168207     </RMSE>
 <CORR>   1.40129846E-45 </CORR>
 </EXP>
 </STATION>
 <STATION>
 <MEAN_OBS>   2.42614889     </MEAN_OBS>
 <STDV_OBS>   1.11825931     </STDV_OBS>
 <EXP>
 <ID>        2881 </ID>
 <NAME>REF</NAME>
 <NUM>        3194 </NUM>
 <MEAN>   2.41801691     </MEAN>
 <STDV>   5.66106606E-11 </STDV>
 <BIAS>  0.270912588     </BIAS>
 <RMSE>  0.974627614     </RMSE>
 <CORR>   5.65998359E-11 </CORR>
 </EXP>
 <EXP>
 <ID>        2881 </ID>
 <NAME>SCATT</NAME>
 <NUM>        3194 </NUM>
 <MEAN>   1.40129846E-45 </MEAN>
 <STDV>   1.40129846E-45 </STDV>
 <BIAS>  0.268924773     </BIAS>
 <RMSE>  0.974976778     </RMSE>
 <CORR>   1.40129846E-45 </CORR>
 </EXP>
 </STATION>
 <STATION>
 <MEAN_OBS>   1.92140424     </MEAN_OBS>
 <STDV_OBS>   1.12769735     </STDV_OBS>
 <EXP>
 <ID>        2720 </ID>
 <NAME>REF</NAME>
 <NUM>        3194 </NUM>
 <MEAN>   1.91953564     </MEAN>
 <STDV>   5.66107716E-11 </STDV>
 <BIAS>  0.372953176     </BIAS>
 <RMSE>  0.943408430     </RMSE>
 <CORR>   5.65683611E-11 </CORR>
 </EXP>
 <EXP>
 <ID>        2720 </ID>
 <NAME>SCATT</NAME>
 <NUM>        3194 </NUM>
 <MEAN>   0.00000000     </MEAN>
 <STDV>   1.40129846E-45 </STDV>
 <BIAS>  0.370099664     </BIAS>
 <RMSE>  0.944745362     </RMSE>
 <CORR>   1.40129846E-45 </CORR>
 </EXP>
 </STATION>
 <STATION>
 <MEAN_OBS>   2.14958668     </MEAN_OBS>
 <STDV_OBS>   1.07956016     </STDV_OBS>
 <EXP>
 <ID>        2824 </ID>
 <NAME>REF</NAME>
 <NUM>        3194 </NUM>
 <MEAN>   2.04269695     </MEAN>
 <STDV>  -6.42552866E-20 </STDV>
 <BIAS>  0.248880938     </BIAS>
 <RMSE>  0.973459005     </RMSE>
 <CORR>   5.65694713E-11 </CORR>
 </EXP>
 <EXP>
 <ID>        2824 </ID>
 <NAME>SCATT</NAME>
 <NUM>        3194 </NUM>
 <MEAN>   1.40129846E-45 </MEAN>
 <STDV>   0.00000000     </STDV>
 <BIAS>  0.233053535     </BIAS>
 <RMSE>  0.977902710     </RMSE>
 <CORR>   1.40129846E-45 </CORR>
 </EXP>
 </STATION>
 <STATION>
 <MEAN_OBS>   1.82135057     </MEAN_OBS>
 <STDV_OBS>   1.07992995     </STDV_OBS>
 <EXP>
 <ID>        2816 </ID>
 <NAME>REF</NAME>
 <NUM>        3194 </NUM>
 <MEAN>   1.74931669     </MEAN>
 <STDV>   5.65683611E-11 </STDV>
 <BIAS>  0.363990098     </BIAS>
 <RMSE>  0.943560421     </RMSE>
 <CORR>   5.65998359E-11 </CORR>
 </EXP>
 <EXP>
 <ID>        2816 </ID>
 <NAME>SCATT</NAME>
 <NUM>        3194 </NUM>
 <MEAN>   1.40129846E-45 </MEAN>
 <STDV>   1.40129846E-45 </STDV>
 <BIAS>  0.355243772     </BIAS>
 <RMSE>  0.946398437     </RMSE>
 <CORR>   1.40129846E-45 </CORR>
 </EXP>
 </STATION>
 <STATION>
 <MEAN_OBS>   2.13346410     </MEAN_OBS>
 <STDV_OBS>   1.11327982     </STDV_OBS>
 <EXP>
 <ID>        1059 </ID>
 <NAME>REF</NAME>
 <NUM>        3194 </NUM>
 <MEAN>   2.22753024     </MEAN>
 <STDV>   5.65999470E-11 </STDV>
 <BIAS>  0.376416206     </BIAS>
 <RMSE>  0.939122260     </RMSE>
 <CORR>   5.65684721E-11 </CORR>
 </EXP>
 <EXP>
 <ID>        1059 </ID>
 <NAME>SCATT</NAME>
 <NUM>        3194 </NUM>
 <MEAN>   1.40129846E-45 </MEAN>
 <STDV>   1.40129846E-45 </STDV>
 <BIAS>  0.382874578     </BIAS>
 <RMSE>  0.939447224     </RMSE>
 <CORR>   1.40129846E-45 </CORR>
 </EXP>
 </STATION>
 <STATION>
 <MEAN_OBS>   2.44831824     </MEAN_OBS>
 <STDV_OBS>   1.07806432     </STDV_OBS>
 <EXP>
 <ID>        1037 </ID>
 <NAME>REF</NAME>
 <NUM>        3194 </NUM>
 <MEAN>   2.45547652     </MEAN>
 <STDV>   5.65693603E-11 </STDV>
 <BIAS>  0.362568229     </BIAS>
 <RMSE>  0.941093743     </RMSE>
 <CORR>   5.65694713E-11 </CORR>
 </EXP>
 <EXP>
 <ID>        1037 </ID>
 <NAME>SCATT</NAME>
 <NUM>        3194 </NUM>
 <MEAN>   1.40129846E-45 </MEAN>
 <STDV>   1.40129846E-45 </STDV>
 <BIAS>  0.362913400     </BIAS>
 <RMSE>  0.941674113     </RMSE>
 <CORR>   1.40129846E-45 </CORR>
 </EXP>
 </STATION>
 <STATION>
 <MEAN_OBS>   1.60468078     </MEAN_OBS>
 <STDV_OBS>   1.08539844     </STDV_OBS>
 <EXP>
 <ID>        1058 </ID>
 <NAME>REF</NAME>
 <NUM>        3194 </NUM>
 <MEAN>   1.89222753     </MEAN>
 <STDV> -0.317637920     </STDV>
 <BIAS>  0.432376355     </BIAS>
 <RMSE>  0.918551981     </RMSE>
 <CORR>   5.65998359E-11 </CORR>
 </EXP>
 <EXP>
 <ID>        1058 </ID>
 <NAME>SCATT</NAME>
 <NUM>        3194 </NUM>
 <MEAN>   1.40129846E-45 </MEAN>
 <STDV>   1.40129846E-45 </STDV>
 <BIAS>  0.426330268     </BIAS>
 <RMSE>  0.921704292     </RMSE>
 <CORR>   1.40129846E-45 </CORR>
 </EXP>
 </STATION>
 <STATION>
 <MEAN_OBS>   2.53780985     </MEAN_OBS>
 <STDV_OBS>   1.08330309     </STDV_OBS>
 <EXP>
 <ID>        1092 </ID>
 <NAME>REF</NAME>
 <NUM>        3170 </NUM>
 <MEAN>   2.43898416     </MEAN>
 <STDV>   5.66106606E-11 </STDV>
 <BIAS>  0.361662209     </BIAS>
 <RMSE>  0.943073034     </RMSE>
 <CORR>   5.65684721E-11 </CORR>
 </EXP>
 <EXP>
 <ID>        1092 </ID>
 <NAME>SCATT</NAME>
 <NUM>        3170 </NUM>
 <MEAN>   1.40129846E-45 </MEAN>
 <STDV>   1.40129846E-45 </STDV>
 <BIAS>  0.350169986     </BIAS>
 <RMSE>  0.947004199     </RMSE>
 <CORR>   1.40129846E-45 </CORR>
 </EXP>
 </STATION>
 <STATION>
 <MEAN_OBS>   3.84993935     </MEAN_OBS>
 <STDV_OBS>   1.27348650     </STDV_OBS>
 <EXP>
 <ID>        1107 </ID>
 <NAME>REF</NAME>
 <NUM>        3194 </NUM>
 <MEAN>   3.63322496     </MEAN>
 <STDV>   5.66107716E-11 </STDV>
 <BIAS>  0.373098046     </BIAS>
 <RMSE>  0.957610190     </RMSE>
 <CORR>   5.65694713E-11 </CORR>
 </EXP>
 <EXP>
 <ID>        1107 </ID>
 <NAME>SCATT</NAME>
 <NUM>        3194 </NUM>
 <MEAN>   0.00000000     </MEAN>
 <STDV>   1.40129846E-45 </STDV>
 <BIAS>  0.371324360     </BIAS>
 <RMSE>  0.956984043     </RMSE>
 <CORR>   1.40129846E-45 </CORR>
 </EXP>
 </STATION>
 <STATION>
 <MEAN_OBS>   1.96376693     </MEAN_OBS>
 <STDV_OBS>   1.17597115     </STDV_OBS>
 <EXP>
 <ID>        1076 </ID>
 <NAME>REF</NAME>
 <NUM>        3194 </NUM>
 <MEAN>   2.14669442     </MEAN>
 <STDV>  -6.42552866E-20 </STDV>
 <BIAS>  0.446486831     </BIAS>
 <RMSE>  0.932076633     </RMSE>
 <CORR>   5.65998359E-11 </CORR>
 </EXP>
 <EXP>
 <ID>        1076 </ID>
 <NAME>SCATT</NAME>
 <NUM>        3194 </NUM>
 <MEAN>   1.40129846E-45 </MEAN>
 <STDV>   0.00000000     </STDV>
 <BIAS>  0.443145692     </BIAS>
 <RMSE>  0.933005512     </RMSE>
 <CORR>   1.40129846E-45 </CORR>
 </EXP>
 </STATION>
 <STATION>
 <MEAN_OBS>   3.12565851     </MEAN_OBS>
 <STDV_OBS>   1.22520304     </STDV_OBS>
 <EXP>
 <ID>        1122 </ID>
 <NAME>REF</NAME>
 <NUM>        3184 </NUM>
 <MEAN>   3.22489142     </MEAN>
 <STDV>   5.65683611E-11 </STDV>
 <BIAS>  0.340922415     </BIAS>
 <RMSE>  0.962452114     </RMSE>
 <CORR>   5.65684721E-11 </CORR>
 </EXP>
 <EXP>
 <ID>        1122 </ID>
 <NAME>SCATT</NAME>
 <NUM>        3184 </NUM>
 <MEAN>   1.40129846E-45 </MEAN>
 <STDV>   1.40129846E-45 </STDV>
 <BIAS>  0.339320749     </BIAS>
 <RMSE>  0.962590873     </RMSE>
 <CORR>   1.40129846E-45 </CORR>
 </EXP>
 </STATION>
 <STATION>
 <MEAN_OBS>   2.72634125     </MEAN_OBS>
 <STDV_OBS>   1.00732863     </STDV_OBS>
 <EXP>
 <ID>        1098 </ID>
 <NAME>REF</NAME>
 <NUM>        3194 </NUM>
 <MEAN>   2.63408446     </MEAN>
 <STDV>   5.65693603E-11 </STDV>
 <BIAS>  0.375237018     </BIAS>
 <RMSE>  0.929260015     </RMSE>
 <CORR>   5.65998359E-11 </CORR>
 </EXP>
 <EXP>
 <ID>        1098 </ID>
 <NAME>SCATT</NAME>
 <NUM>        3194 </NUM>
 <MEAN>   1.40129846E-45 </MEAN>
 <STDV>   1.40129846E-45 </STDV>
 <BIAS>  0.350837737     </BIAS>
 <RMSE>  0.941615283     </RMSE>
 <CORR>   1.40129846E-45 </CORR>
 </EXP>
 </STATION>
 <STATION>
 <MEAN_OBS>   1.43090558     </MEAN_OBS>
 <STDV_OBS>  0.745211244     </STDV_OBS>
 <EXP>
 <ID>        1003 </ID>
 <NAME>REF</NAME>
 <NUM>        3180 </NUM>
 <MEAN>   1.38057756     </MEAN>
 <STDV> -0.317637920     </STDV>
 <BIAS>  0.242634818     </BIAS>
 <RMSE>  0.947343886     </RMSE>
 <CORR>   5.65684721E-11 </CORR>
 </EXP>
 <EXP>
 <ID>        1003 </ID>
 <NAME>SCATT</NAME>
 <NUM>        3180 </NUM>
 <MEAN>   1.40129846E-45 </MEAN>
 <STDV>   1.40129846E-45 </STDV>
 <BIAS>  0.236610904     </BIAS>
 <RMSE>  0.950745165     </RMSE>
 <CORR>   1.40129846E-45 </CORR>
 </EXP>
 </STATION>
 <STATION>
 <MEAN_OBS>   1.08935511     </MEAN_OBS>
 <STDV_OBS>  0.400461107     </STDV_OBS>
 <EXP>
 <ID>        1007 </ID>
 <NAME>REF</NAME>
 <NUM>        3194 </NUM>
 <MEAN>  0.946112990     </MEAN>
 <STDV>   5.66106606E-11 </STDV>
 <BIAS>  0.209255770     </BIAS>
 <RMSE>  0.871638954     </RMSE>
 <CORR>   5.65694713E-11 </CORR>
 </EXP>
 <EXP>
 <ID>        1007 </ID>
 <NAME>SCATT</NAME>
 <NUM>        3194 </NUM>
 <MEAN>   1.40129846E-45 </MEAN>
 <STDV>   1.40129846E-45 </STDV>
 <BIAS>  0.210090250     </BIAS>
 <RMSE>  0.871090412     </RMSE>
 <CORR>   1.40129846E-45 </CORR>
 </EXP>
 </STATION>
 <STATION>
 <MEAN_OBS>   1.48459709     </MEAN_OBS>
 <STDV_OBS>   1.08669698     </STDV_OBS>
 <EXP>
 <ID>        1047 </ID>
 <NAME>REF</NAME>
 <NUM>         896 </NUM>
 <MEAN>   1.79728615     </MEAN>
 <STDV>   5.66107716E-11 </STDV>
 <BIAS>  0.485148728     </BIAS>
 <RMSE>  0.896712720     </RMSE>
 <CORR>   5.65998359E-11 </CORR>
 </EXP>
 <EXP>
 <ID>        1047 </ID>
 <NAME>SCATT</NAME>
 <NUM>         896 </NUM>
 <MEAN>   0.00000000     </MEAN>
 <STDV>   1.40129846E-45 </STDV>
 <BIAS>  0.468419015     </BIAS>
 <RMSE>  0.903831720     </RMSE>
 <CORR>   1.40129846E-45 </CORR>
 </EXP>
 </STATION>
 <STATION>
 <MEAN_OBS>   3.93707895     </MEAN_OBS>
 <STDV_OBS>   1.06304264     </STDV_OBS>
 <EXP>
 <ID>        1102 </ID>
 <NAME>REF</NAME>
 <NUM>        3127 </NUM>
 <MEAN>   3.81792974     </MEAN>
 <STDV>   5.65694713E-11 </STDV>
 <BIAS>  0.355679452     </BIAS>
 <RMSE>  0.943095982     </RMSE>
 <CORR>   5.65684721E-11 </CORR>
 </EXP>
 <EXP>
 <ID>        1102 </ID>
 <NAME>SCATT</NAME>
 <NUM>        3127 </NUM>
 <MEAN>   1.40129846E-45 </MEAN>
 <STDV>   1.40129846E-45 </STDV>
 <BIAS>  0.355364740     </BIAS>
 <RMSE>  0.942797065     </RMSE>
 <CORR>   1.40129846E-45 </CORR>
 </EXP>
 </STATION>
 <STATION>
 <MEAN_OBS>   3.08717442     </MEAN_OBS>
 <STDV_OBS>   1.01655948     </STDV_OBS>
 <EXP>
 <ID>        1281 </ID>
 <NAME>REF</NAME>
 <NUM>        3194 </NUM>
 <MEAN>   3.05904198     </MEAN>
 <STDV>   5.65683611E-11 </STDV>
 <BIAS>  0.312773407     </BIAS>
 <RMSE>  0.956176996     </RMSE>
 <CORR>  -6.42552866E-20 </CORR>
 </EXP>
 <EXP>
 <ID>        1281 </ID>
 <NAME>SCATT</NAME>
 <NUM>        3194 </NUM>
 <MEAN>   1.40129846E-45 </MEAN>
 <STDV>   1.40129846E-45 </STDV>
 <BIAS>  0.309488446     </BIAS>
 <RMSE>  0.957138956     </RMSE>
 <CORR>   0.00000000     </CORR>
 </EXP>
 </STATION>
 <STATION>
 <MEAN_OBS>   3.75456715     </MEAN_OBS>
 <STDV_OBS>   1.23508060     </STDV_OBS>
 <EXP>
 <ID>        1121 </ID>
 <NAME>REF</NAME>
 <NUM>        3193 </NUM>
 <MEAN>   3.62038064     </MEAN>
 <STDV>   5.65999470E-11 </STDV>
 <BIAS>  0.381901115     </BIAS>
 <RMSE>  0.952284515     </RMSE>
 <CORR>   5.65998359E-11 </CORR>
 </EXP>
 <EXP>
 <ID>        1121 </ID>
 <NAME>SCATT</NAME>
 <NUM>        3193 </NUM>
 <MEAN>   1.40129846E-45 </MEAN>
 <STDV>   1.40129846E-45 </STDV>
 <BIAS>  0.384008795     </BIAS>
 <RMSE>  0.950916588     </RMSE>
 <CORR>   1.40129846E-45 </CORR>
 </EXP>
 </STATION>
</STAT>
